{"ModelName":"Apple-iPhone7Plus-MatteBlack","InspectionTime":"2019/11/25 10:57:58","Index":"353821085453464","FileName":"D:\\150\\20191122-iPhone7Plus-MatteBlack\\353821085453464\\defect.xml","CriteriaFileName":"C:\\ProgramData\\Futuredial\\AVIA\\FDGrading\\FDData\\CriteriaXML\\Grading CriteriaVZW-Chris.xml","Grade":"D+","GradingLevels":[{"GradingLevel":"A+","Comment":["*****Current Grade = A+, Current Surface = A*****","Defect Type Scratch, Defects number = 47 on A Surface","\tDefectLength = 1.6125, DefectWidth = 0.625, DefectContrast = 25","\tDefectLength = 1.1, DefectWidth = 0.25, DefectContrast = 34","\tDefectLength = 0.8875, DefectWidth = 0.675, DefectContrast = 29","\tDefectLength = 0.6, DefectWidth = 0.1625, DefectContrast = 21","\tDefectLength = 0.8625, DefectWidth = 0.3625, DefectContrast = 34","\tDefectLength = 1.0125, DefectWidth = 0.4625, DefectContrast = 22","\tDefectLength = 1.1, DefectWidth = 0.2625, DefectContrast = 30","\tDefectLength = 0.8375, DefectWidth = 0.1375, DefectContrast = 27","\tDefectLength = 0.5125, DefectWidth = 0.1625, DefectContrast = 19","\tDefectLength = 0.5375, DefectWidth = 0.35, DefectContrast = 19","\tDefectLength = 0.5, DefectWidth = 0.1875, DefectContrast = 37","\tDefectLength = 1.05, DefectWidth = 0.5, DefectContrast = 21","\tDefectLength = 0.4, DefectWidth = 0.375, DefectContrast = 24","\tDefectLength = 0.6, DefectWidth = 0.4125, DefectContrast = 31","\tDefectLength = 0.775, DefectWidth = 0.65, DefectContrast = 17","\tDefectLength = 0.8, DefectWidth = 0.0625, DefectContrast = 8","\tDefectLength = 0.4875, DefectWidth = 0.2875, DefectContrast = 17","\tDefectLength = 0.575, DefectWidth = 0.3125, DefectContrast = 26","\tDefectLength = 0.65, DefectWidth = 0.175, DefectContrast = 31","\tDefectLength = 0.5625, DefectWidth = 0.125, DefectContrast = 19","\tDefectLength = 1.0375, DefectWidth = 0.1375, DefectContrast = 26","\tDefectLength = 1.175, DefectWidth = 0.35, DefectContrast = 29","\tDefectLength = 0.5875, DefectWidth = 0.2625, DefectContrast = 19","\tDefectLength = 0.85, DefectWidth = 0.3125, DefectContrast = 22","\tDefectLength = 0.6125, DefectWidth = 0.2125, DefectContrast = 15","\tDefectLength = 0.8, DefectWidth = 0.3375, DefectContrast = 25","\tDefectLength = 0.5375, DefectWidth = 0.2375, DefectContrast = 13","\tDefectLength = 0.425, DefectWidth = 0.35, DefectContrast = 18","\tDefectLength = 0.6625, DefectWidth = 0.2, DefectContrast = 22","\tDefectLength = 0.65, DefectWidth = 0.15, DefectContrast = 5","\tDefectLength = 3.575, DefectWidth = 0.2, DefectContrast = 2","\tDefectLength = 0.675, DefectWidth = 0.175, DefectContrast = 3","\tDefectLength = 0.575, DefectWidth = 0.25, DefectContrast = 5","\tDefectLength = 0.4, DefectWidth = 0.375, DefectContrast = 4","\tDefectLength = 1.025, DefectWidth = 0.475, DefectContrast = 4","\tDefectLength = 0.5, DefectWidth = 0.225, DefectContrast = 3","\tDefectLength = 0.9, DefectWidth = 0.625, DefectContrast = 5","\tDefectLength = 1.1, DefectWidth = 0.2, DefectContrast = 8","\tDefectLength = 1.575, DefectWidth = 0.575, DefectContrast = 5","\tDefectLength = 1.05, DefectWidth = 0.5, DefectContrast = 5","\tDefectLength = 0.55, DefectWidth = 0.15, DefectContrast = 3","\tDefectLength = 0.9, DefectWidth = 0.3, DefectContrast = 7","\tDefectLength = 1, DefectWidth = 0.1, DefectContrast = 6","\tDefectLength = 0.5, DefectWidth = 0.15, DefectContrast = 8","\tDefectLength = 1.1, DefectWidth = 0.225, DefectContrast = 7","\tDefectLength = 0.425, DefectWidth = 0.4, DefectContrast = 3","\tDefectLength = 0.325, DefectWidth = 0.175, DefectContrast = 1","Defect Type Nick, Defects number = 37 on A Surface","\tDefectLength = 0.2875, DefectWidth = 0.15, DefectContrast = 16","\tDefectLength = 0.7375, DefectWidth = 0.525, DefectContrast = 28","\tDefectLength = 0.2625, DefectWidth = 0.1125, DefectContrast = 28","\tDefectLength = 0.5375, DefectWidth = 0.325, DefectContrast = 21","\tDefectLength = 0.3, DefectWidth = 0.1625, DefectContrast = 20","\tDefectLength = 0.2625, DefectWidth = 0.125, DefectContrast = 15","\tDefectLength = 0.3625, DefectWidth = 0.2625, DefectContrast = 15","\tDefectLength = 0.7875, DefectWidth = 0.5, DefectContrast = 39","\tDefectLength = 0.25, DefectWidth = 0.225, DefectContrast = 36","\tDefectLength = 0.5125, DefectWidth = 0.3875, DefectContrast = 14","\tDefectLength = 0.225, DefectWidth = 0.1375, DefectContrast = 19","\tDefectLength = 0.2125, DefectWidth = 0.2125, DefectContrast = 48","\tDefectLength = 0.1875, DefectWidth = 0.1875, DefectContrast = 23","\tDefectLength = 0.725, DefectWidth = 0.4125, DefectContrast = 16","\tDefectLength = 0.3, DefectWidth = 0.125, DefectContrast = 25","\tDefectLength = 0.2, DefectWidth = 0.175, DefectContrast = 29","\tDefectLength = 0.4, DefectWidth = 0.2375, DefectContrast = 10","\tDefectLength = 0.225, DefectWidth = 0.15, DefectContrast = 34","\tDefectLength = 0.2125, DefectWidth = 0.0875, DefectContrast = 29","\tDefectLength = 0.2625, DefectWidth = 0.225, DefectContrast = 19","\tDefectLength = 0.2375, DefectWidth = 0.1875, DefectContrast = 26","\tDefectLength = 0.225, DefectWidth = 0.2, DefectContrast = 22","\tDefectLength = 0.2, DefectWidth = 0.15, DefectContrast = 20","\tDefectLength = 16.45, DefectWidth = 2.2, DefectContrast = 9","\tDefectLength = 5.5625, DefectWidth = 5.55, DefectContrast = 30","\tDefectLength = 2.4625, DefectWidth = 2.2625, DefectContrast = 8","\tDefectLength = 1.225, DefectWidth = 0.525, DefectContrast = 35","\tDefectLength = 1.2, DefectWidth = 0.8125, DefectContrast = 34","\tDefectLength = 1.08, DefectWidth = 0.5, DefectContrast = 39","\tDefectLength = 1.24, DefectWidth = 1.04, DefectContrast = 31","\tDefectLength = 1.8, DefectWidth = 0.26, DefectContrast = 98","\tDefectLength = 1.8, DefectWidth = 0.34, DefectContrast = 73","\tDefectLength = 1.8, DefectWidth = 0.38, DefectContrast = 87","\tDefectLength = 0.98, DefectWidth = 0.34, DefectContrast = 41","\tDefectLength = 1.36, DefectWidth = 1.12, DefectContrast = 32","\tDefectLength = 1.4, DefectWidth = 1.14, DefectContrast = 32","\tDefectLength = 1.2, DefectWidth = 1.14, DefectContrast = 26","Defect Type Dent, Defects number = 54 on A Surface","\tDefectLength = 0.525, DefectWidth = 0.35, DefectContrast = 18","\tDefectLength = 1.1625, DefectWidth = 0.525, DefectContrast = 18","\tDefectLength = 0.45, DefectWidth = 0.3625, DefectContrast = 13","\tDefectLength = 0.65, DefectWidth = 0.3375, DefectContrast = 31","\tDefectLength = 16.825, DefectWidth = 3.2375, DefectContrast = 27","\tDefectLength = 0.35, DefectWidth = 0.3125, DefectContrast = 16","\tDefectLength = 3.75, DefectWidth = 3.75, DefectContrast = 53","\tDefectLength = 0.625, DefectWidth = 0.225, DefectContrast = 11","\tDefectLength = 1.3, DefectWidth = 0.5875, DefectContrast = 61","\tDefectLength = 0.3375, DefectWidth = 0.2875, DefectContrast = 17","\tDefectLength = 0.45, DefectWidth = 0.4375, DefectContrast = 16","\tDefectLength = 0.95, DefectWidth = 0.675, DefectContrast = 15","\tDefectLength = 20.525, DefectWidth = 4.2125, DefectContrast = 100","\tDefectLength = 2.7125, DefectWidth = 1.975, DefectContrast = 22","\tDefectLength = 7.125, DefectWidth = 1.775, DefectContrast = 34","\tDefectLength = 2.075, DefectWidth = 1.4375, DefectContrast = 17","\tDefectLength = 1.1125, DefectWidth = 0.2, DefectContrast = 20","\tDefectLength = 1.4625, DefectWidth = 0.2375, DefectContrast = 25","\tDefectLength = 1.9375, DefectWidth = 0.25, DefectContrast = 24","\tDefectLength = 0.5, DefectWidth = 0.175, DefectContrast = 24","\tDefectLength = 0.3125, DefectWidth = 0.275, DefectContrast = 14","\tDefectLength = 0.625, DefectWidth = 0.4125, DefectContrast = 16","\tDefectLength = 0.4, DefectWidth = 0.3875, DefectContrast = 35","\tDefectLength = 0.35, DefectWidth = 0.275, DefectContrast = 14","\tDefectLength = 0.575, DefectWidth = 0.5, DefectContrast = 33","\tDefectLength = 0.5875, DefectWidth = 0.5375, DefectContrast = 38","\tDefectLength = 0.5875, DefectWidth = 0.425, DefectContrast = 24","\tDefectLength = 0.4375, DefectWidth = 0.3125, DefectContrast = 15","\tDefectLength = 1.625, DefectWidth = 1.2625, DefectContrast = 20","\tDefectLength = 2.2, DefectWidth = 0.55, DefectContrast = 18","\tDefectLength = 0.7875, DefectWidth = 0.3875, DefectContrast = 15","\tDefectLength = 0.425, DefectWidth = 0.2375, DefectContrast = 10","\tDefectLength = 0.575, DefectWidth = 0.55, DefectContrast = 37","\tDefectLength = 0.2625, DefectWidth = 0.2625, DefectContrast = 16","\tDefectLength = 0.225, DefectWidth = 0.1625, DefectContrast = 30","\tDefectLength = 1.3125, DefectWidth = 0.2375, DefectContrast = 39","\tDefectLength = 0.175, DefectWidth = 0.1625, DefectContrast = 31","\tDefectLength = 1.8625, DefectWidth = 0.2375, DefectContrast = 35","\tDefectLength = 0.2375, DefectWidth = 0.1625, DefectContrast = 33","\tDefectLength = 3.1875, DefectWidth = 0.3125, DefectContrast = 46","\tDefectLength = 0.225, DefectWidth = 0.1625, DefectContrast = 31","\tDefectLength = 1.25, DefectWidth = 0.2375, DefectContrast = 35","\tDefectLength = 3.8, DefectWidth = 0.2875, DefectContrast = 66","\tDefectLength = 0.2, DefectWidth = 0.1625, DefectContrast = 28","\tDefectLength = 0.35, DefectWidth = 0.15, DefectContrast = 28","\tDefectLength = 0.8875, DefectWidth = 0.2125, DefectContrast = 102","\tDefectLength = 0.6, DefectWidth = 0.15, DefectContrast = 89","\tDefectLength = 0.325, DefectWidth = 0.15, DefectContrast = 90","\tDefectLength = 0.35, DefectWidth = 0.125, DefectContrast = 88","\tDefectLength = 0.3125, DefectWidth = 0.15, DefectContrast = 88","\tDefectLength = 0.2625, DefectWidth = 0.0875, DefectContrast = 91","\tDefectLength = 1.8, DefectWidth = 0.18, DefectContrast = 156","\tDefectLength = 1.8, DefectWidth = 0.08, DefectContrast = 194","\tDefectLength = 1.8, DefectWidth = 0.14, DefectContrast = 213","The defect is too big: surface is A, defect type is Scratch, defect length is 1.6125,defect width is 0.625, defect area_mm is 0.08969, defect contrast is 25","The defect is too big: surface is A, defect type is Scratch, defect length is 0.8875,defect width is 0.675, defect area_mm is 0.06672, defect contrast is 29","The defect is too big: surface is A, defect type is Scratch, defect length is 1.0125,defect width is 0.4625, defect area_mm is 0.06266, defect contrast is 22","defect count is over Scratch limitation(3)","The defect is too big: surface is A, defect type is Scratch, defect length is 1.05,defect width is 0.5, defect area_mm is 0.06922, defect contrast is 21","The defect is too big: surface is A, defect type is Scratch, defect length is 0.775,defect width is 0.65, defect area_mm is 0.05703, defect contrast is 17","The defect is too big: surface is A, defect type is Scratch, defect length is 1.025,defect width is 0.475, defect area_mm is 0.06125, defect contrast is 4","The defect is too big: surface is A, defect type is Scratch, defect length is 0.9,defect width is 0.625, defect area_mm is 0.06125, defect contrast is 5","The defect is too big: surface is A, defect type is Scratch, defect length is 1.575,defect width is 0.575, defect area_mm is 0.08688, defect contrast is 5","The defect is too big: surface is A, defect type is Scratch, defect length is 1.05,defect width is 0.5, defect area_mm is 0.06188, defect contrast is 5","defect count is over Nick limitation(0)","defect count is over Dent limitation(0)","Surface Defect Count is over limitation(12)","*****Current Grade = A+, Current Surface = B*****","Defect Type Nick, Defects number = 42 on B Surface","\tDefectLength = 15.74, DefectWidth = 0.5, DefectContrast = 17","\tDefectLength = 30.32, DefectWidth = 0.54, DefectContrast = 21","\tDefectLength = 11.38, DefectWidth = 1.42, DefectContrast = 27","\tDefectLength = 14.1984, DefectWidth = 0.2592, DefectContrast = 12","\tDefectLength = 12.2016, DefectWidth = 0.1824, DefectContrast = 14","\tDefectLength = 3.8304, DefectWidth = 0.1152, DefectContrast = 7","\tDefectLength = 1.7088, DefectWidth = 1.4304, DefectContrast = 9","\tDefectLength = 0.8352, DefectWidth = 0.1344, DefectContrast = 7","\tDefectLength = 0.5184, DefectWidth = 0.3936, DefectContrast = 12","\tDefectLength = 0.3168, DefectWidth = 0.192, DefectContrast = 9","\tDefectLength = 0.624, DefectWidth = 0.1824, DefectContrast = 8","\tDefectLength = 0.672, DefectWidth = 0.3552, DefectContrast = 8","\tDefectLength = 0.4608, DefectWidth = 0.3168, DefectContrast = 10","\tDefectLength = 0.528, DefectWidth = 0.1728, DefectContrast = 8","\tDefectLength = 2.784, DefectWidth = 1.3056, DefectContrast = 7","\tDefectLength = 1.2384, DefectWidth = 0.1152, DefectContrast = 9","\tDefectLength = 11.8368, DefectWidth = 0.288, DefectContrast = 13","\tDefectLength = 0.48, DefectWidth = 0.2016, DefectContrast = 8","\tDefectLength = 1.8432, DefectWidth = 0.1344, DefectContrast = 10","\tDefectLength = 1.3152, DefectWidth = 0.2304, DefectContrast = 6","\tDefectLength = 10.1856, DefectWidth = 0.192, DefectContrast = 17","\tDefectLength = 5.3472, DefectWidth = 0.1152, DefectContrast = 8","\tDefectLength = 5.5776, DefectWidth = 0.144, DefectContrast = 8","\tDefectLength = 1.8432, DefectWidth = 0.1536, DefectContrast = 6","\tDefectLength = 0.7968, DefectWidth = 0.192, DefectContrast = 12","\tDefectLength = 3.456, DefectWidth = 0.1824, DefectContrast = 8","\tDefectLength = 1.0272, DefectWidth = 0.1152, DefectContrast = 6","\tDefectLength = 1.5456, DefectWidth = 0.1536, DefectContrast = 12","\tDefectLength = 11.8368, DefectWidth = 0.3264, DefectContrast = 11","\tDefectLength = 0.9408, DefectWidth = 0.096, DefectContrast = 7","\tDefectLength = 1.536, DefectWidth = 0.1152, DefectContrast = 7","\tDefectLength = 10.5408, DefectWidth = 0.1344, DefectContrast = 17","\tDefectLength = 2.3904, DefectWidth = 0.1248, DefectContrast = 7","\tDefectLength = 8.0352, DefectWidth = 0.2112, DefectContrast = 9","\tDefectLength = 0.5568, DefectWidth = 0.4896, DefectContrast = 6","\tDefectLength = 3.744, DefectWidth = 0.1248, DefectContrast = 7","\tDefectLength = 1.7472, DefectWidth = 0.8736, DefectContrast = 9","\tDefectLength = 0.576, DefectWidth = 0.3936, DefectContrast = 14","\tDefectLength = 11.8944, DefectWidth = 0.2496, DefectContrast = 10","\tDefectLength = 9.1776, DefectWidth = 0.1824, DefectContrast = 13","\tDefectLength = 1.9392, DefectWidth = 0.1056, DefectContrast = 5","\tDefectLength = 1.8528, DefectWidth = 0.1152, DefectContrast = 6","Defect Type Dent, Defects number = 14 on B Surface","\tDefectLength = 7.44, DefectWidth = 1.56, DefectContrast = 33","\tDefectLength = 5.26, DefectWidth = 1.24, DefectContrast = 21","\tDefectLength = 1.4304, DefectWidth = 0.1056, DefectContrast = 14","\tDefectLength = 1.104, DefectWidth = 0.1632, DefectContrast = 17","\tDefectLength = 0.2016, DefectWidth = 0.1728, DefectContrast = 21","\tDefectLength = 0.8928, DefectWidth = 0.144, DefectContrast = 27","\tDefectLength = 0.7584, DefectWidth = 0.1056, DefectContrast = 18","\tDefectLength = 0.9696, DefectWidth = 0.1056, DefectContrast = 20","\tDefectLength = 0.4224, DefectWidth = 0.096, DefectContrast = 21","\tDefectLength = 0.6336, DefectWidth = 0.0864, DefectContrast = 25","\tDefectLength = 1.6032, DefectWidth = 0.096, DefectContrast = 19","\tDefectLength = 0.2688, DefectWidth = 0.144, DefectContrast = 29","\tDefectLength = 58.6, DefectWidth = 1.48, DefectContrast = 25","\tDefectLength = 4.42, DefectWidth = 1, DefectContrast = 20","defect count is over Nick limitation(0)","defect count is over Dent limitation(0)","Surface Defect Count is over limitation(3)","Grade max total defects are over limitation(3)."],"GradeMaxDefectTotal":[3,185],"SurfaceItems":[{"SurfaceName":"AA","SurfaceTotalCount":[3,0],"SurfaceGroup":{"max_defect_none":[-1,0],"max_defect_others":[0,0],"max_defect_others_Scratch":[0,0],"max_defect_others_Nick":[0,0],"max_defect_others_Dent":[0,0],"max_defect_others_Crack":[0,0],"max_defect_others_Discoloration":[0,0],"max_defect_others_GroupPindot":[0,0],"max_defect_others_DifferentScreen":[0,0],"max_defect_others_AlignmentFailed":[0,0]},"SurfaceZone":{},"DefectItems":{"LogicAnd":{"Scratch":[[0,0]],"Nick":[[0,0]],"Dent":[[0,0]],"Crack":[[0,0]],"Discoloration":[[0,0]],"DifferentScreen":[[0,0]]},"LogicOr":{"GroupPindot":[[0,0]]}}},{"SurfaceName":"A","SurfaceTotalCount":[12,129],"SurfaceGroup":{"max_defect_none":[-1,129],"max_defect_others":[0,0],"max_defect_others_Scratch":[0,9],"max_defect_others_Nick":[0,0],"max_defect_others_Dent":[0,0],"max_defect_others_Crack":[0,0],"max_defect_others_Discoloration":[0,0],"max_defect_others_GroupPindot":[0,0],"max_defect_others_AlignmentFailed":[0,0]},"SurfaceZone":{},"DefectItems":{"LogicAnd":{"Scratch":[[3,38]],"Dent":[[0,54]],"Nick":[[0,37]],"Crack":[[0,0]],"Discoloration":[[0,0]]},"LogicOr":{"GroupPindot":[[0,0]]}}},{"SurfaceName":"B","SurfaceTotalCount":[3,56],"SurfaceGroup":{"max_defect_none":[-1,56],"max_defect_others":[0,0],"max_defect_others_Scratch":[0,0],"max_defect_others_Nick":[0,0],"max_defect_others_Dent":[0,0],"max_defect_others_Crack":[0,0],"max_defect_others_Discoloration":[0,0],"max_defect_others_GroupPindot":[0,0],"max_defect_others_AlignmentFailed":[0,0]},"SurfaceZone":{},"DefectItems":{"LogicAnd":{"Scratch":[[3,0]],"Nick":[[0,42]],"Dent":[[0,14]],"Crack":[[0,0]],"Discoloration":[[0,0]]},"LogicOr":{"GroupPindot":[[0,0]]}}}]},{"GradingLevel":"A","Comment":["*****Current Grade = A, Current Surface = A*****","Defect Type Scratch, Defects number = 47 on A Surface","\tDefectLength = 1.6125, DefectWidth = 0.625, DefectContrast = 25","\tDefectLength = 1.1, DefectWidth = 0.25, DefectContrast = 34","\tDefectLength = 0.8875, DefectWidth = 0.675, DefectContrast = 29","\tDefectLength = 0.6, DefectWidth = 0.1625, DefectContrast = 21","\tDefectLength = 0.8625, DefectWidth = 0.3625, DefectContrast = 34","\tDefectLength = 1.0125, DefectWidth = 0.4625, DefectContrast = 22","\tDefectLength = 1.1, DefectWidth = 0.2625, DefectContrast = 30","\tDefectLength = 0.8375, DefectWidth = 0.1375, DefectContrast = 27","\tDefectLength = 0.5125, DefectWidth = 0.1625, DefectContrast = 19","\tDefectLength = 0.5375, DefectWidth = 0.35, DefectContrast = 19","\tDefectLength = 0.5, DefectWidth = 0.1875, DefectContrast = 37","\tDefectLength = 1.05, DefectWidth = 0.5, DefectContrast = 21","\tDefectLength = 0.4, DefectWidth = 0.375, DefectContrast = 24","\tDefectLength = 0.6, DefectWidth = 0.4125, DefectContrast = 31","\tDefectLength = 0.775, DefectWidth = 0.65, DefectContrast = 17","\tDefectLength = 0.8, DefectWidth = 0.0625, DefectContrast = 8","\tDefectLength = 0.4875, DefectWidth = 0.2875, DefectContrast = 17","\tDefectLength = 0.575, DefectWidth = 0.3125, DefectContrast = 26","\tDefectLength = 0.65, DefectWidth = 0.175, DefectContrast = 31","\tDefectLength = 0.5625, DefectWidth = 0.125, DefectContrast = 19","\tDefectLength = 1.0375, DefectWidth = 0.1375, DefectContrast = 26","\tDefectLength = 1.175, DefectWidth = 0.35, DefectContrast = 29","\tDefectLength = 0.5875, DefectWidth = 0.2625, DefectContrast = 19","\tDefectLength = 0.85, DefectWidth = 0.3125, DefectContrast = 22","\tDefectLength = 0.6125, DefectWidth = 0.2125, DefectContrast = 15","\tDefectLength = 0.8, DefectWidth = 0.3375, DefectContrast = 25","\tDefectLength = 0.5375, DefectWidth = 0.2375, DefectContrast = 13","\tDefectLength = 0.425, DefectWidth = 0.35, DefectContrast = 18","\tDefectLength = 0.6625, DefectWidth = 0.2, DefectContrast = 22","\tDefectLength = 0.65, DefectWidth = 0.15, DefectContrast = 5","\tDefectLength = 3.575, DefectWidth = 0.2, DefectContrast = 2","\tDefectLength = 0.675, DefectWidth = 0.175, DefectContrast = 3","\tDefectLength = 0.575, DefectWidth = 0.25, DefectContrast = 5","\tDefectLength = 0.4, DefectWidth = 0.375, DefectContrast = 4","\tDefectLength = 1.025, DefectWidth = 0.475, DefectContrast = 4","\tDefectLength = 0.5, DefectWidth = 0.225, DefectContrast = 3","\tDefectLength = 0.9, DefectWidth = 0.625, DefectContrast = 5","\tDefectLength = 1.1, DefectWidth = 0.2, DefectContrast = 8","\tDefectLength = 1.575, DefectWidth = 0.575, DefectContrast = 5","\tDefectLength = 1.05, DefectWidth = 0.5, DefectContrast = 5","\tDefectLength = 0.55, DefectWidth = 0.15, DefectContrast = 3","\tDefectLength = 0.9, DefectWidth = 0.3, DefectContrast = 7","\tDefectLength = 1, DefectWidth = 0.1, DefectContrast = 6","\tDefectLength = 0.5, DefectWidth = 0.15, DefectContrast = 8","\tDefectLength = 1.1, DefectWidth = 0.225, DefectContrast = 7","\tDefectLength = 0.425, DefectWidth = 0.4, DefectContrast = 3","\tDefectLength = 0.325, DefectWidth = 0.175, DefectContrast = 1","Defect Type Nick, Defects number = 37 on A Surface","\tDefectLength = 0.2875, DefectWidth = 0.15, DefectContrast = 16","\tDefectLength = 0.7375, DefectWidth = 0.525, DefectContrast = 28","\tDefectLength = 0.2625, DefectWidth = 0.1125, DefectContrast = 28","\tDefectLength = 0.5375, DefectWidth = 0.325, DefectContrast = 21","\tDefectLength = 0.3, DefectWidth = 0.1625, DefectContrast = 20","\tDefectLength = 0.2625, DefectWidth = 0.125, DefectContrast = 15","\tDefectLength = 0.3625, DefectWidth = 0.2625, DefectContrast = 15","\tDefectLength = 0.7875, DefectWidth = 0.5, DefectContrast = 39","\tDefectLength = 0.25, DefectWidth = 0.225, DefectContrast = 36","\tDefectLength = 0.5125, DefectWidth = 0.3875, DefectContrast = 14","\tDefectLength = 0.225, DefectWidth = 0.1375, DefectContrast = 19","\tDefectLength = 0.2125, DefectWidth = 0.2125, DefectContrast = 48","\tDefectLength = 0.1875, DefectWidth = 0.1875, DefectContrast = 23","\tDefectLength = 0.725, DefectWidth = 0.4125, DefectContrast = 16","\tDefectLength = 0.3, DefectWidth = 0.125, DefectContrast = 25","\tDefectLength = 0.2, DefectWidth = 0.175, DefectContrast = 29","\tDefectLength = 0.4, DefectWidth = 0.2375, DefectContrast = 10","\tDefectLength = 0.225, DefectWidth = 0.15, DefectContrast = 34","\tDefectLength = 0.2125, DefectWidth = 0.0875, DefectContrast = 29","\tDefectLength = 0.2625, DefectWidth = 0.225, DefectContrast = 19","\tDefectLength = 0.2375, DefectWidth = 0.1875, DefectContrast = 26","\tDefectLength = 0.225, DefectWidth = 0.2, DefectContrast = 22","\tDefectLength = 0.2, DefectWidth = 0.15, DefectContrast = 20","\tDefectLength = 16.45, DefectWidth = 2.2, DefectContrast = 9","\tDefectLength = 5.5625, DefectWidth = 5.55, DefectContrast = 30","\tDefectLength = 2.4625, DefectWidth = 2.2625, DefectContrast = 8","\tDefectLength = 1.225, DefectWidth = 0.525, DefectContrast = 35","\tDefectLength = 1.2, DefectWidth = 0.8125, DefectContrast = 34","\tDefectLength = 1.08, DefectWidth = 0.5, DefectContrast = 39","\tDefectLength = 1.24, DefectWidth = 1.04, DefectContrast = 31","\tDefectLength = 1.8, DefectWidth = 0.26, DefectContrast = 98","\tDefectLength = 1.8, DefectWidth = 0.34, DefectContrast = 73","\tDefectLength = 1.8, DefectWidth = 0.38, DefectContrast = 87","\tDefectLength = 0.98, DefectWidth = 0.34, DefectContrast = 41","\tDefectLength = 1.36, DefectWidth = 1.12, DefectContrast = 32","\tDefectLength = 1.4, DefectWidth = 1.14, DefectContrast = 32","\tDefectLength = 1.2, DefectWidth = 1.14, DefectContrast = 26","Defect Type Dent, Defects number = 54 on A Surface","\tDefectLength = 0.525, DefectWidth = 0.35, DefectContrast = 18","\tDefectLength = 1.1625, DefectWidth = 0.525, DefectContrast = 18","\tDefectLength = 0.45, DefectWidth = 0.3625, DefectContrast = 13","\tDefectLength = 0.65, DefectWidth = 0.3375, DefectContrast = 31","\tDefectLength = 16.825, DefectWidth = 3.2375, DefectContrast = 27","\tDefectLength = 0.35, DefectWidth = 0.3125, DefectContrast = 16","\tDefectLength = 3.75, DefectWidth = 3.75, DefectContrast = 53","\tDefectLength = 0.625, DefectWidth = 0.225, DefectContrast = 11","\tDefectLength = 1.3, DefectWidth = 0.5875, DefectContrast = 61","\tDefectLength = 0.3375, DefectWidth = 0.2875, DefectContrast = 17","\tDefectLength = 0.45, DefectWidth = 0.4375, DefectContrast = 16","\tDefectLength = 0.95, DefectWidth = 0.675, DefectContrast = 15","\tDefectLength = 20.525, DefectWidth = 4.2125, DefectContrast = 100","\tDefectLength = 2.7125, DefectWidth = 1.975, DefectContrast = 22","\tDefectLength = 7.125, DefectWidth = 1.775, DefectContrast = 34","\tDefectLength = 2.075, DefectWidth = 1.4375, DefectContrast = 17","\tDefectLength = 1.1125, DefectWidth = 0.2, DefectContrast = 20","\tDefectLength = 1.4625, DefectWidth = 0.2375, DefectContrast = 25","\tDefectLength = 1.9375, DefectWidth = 0.25, DefectContrast = 24","\tDefectLength = 0.5, DefectWidth = 0.175, DefectContrast = 24","\tDefectLength = 0.3125, DefectWidth = 0.275, DefectContrast = 14","\tDefectLength = 0.625, DefectWidth = 0.4125, DefectContrast = 16","\tDefectLength = 0.4, DefectWidth = 0.3875, DefectContrast = 35","\tDefectLength = 0.35, DefectWidth = 0.275, DefectContrast = 14","\tDefectLength = 0.575, DefectWidth = 0.5, DefectContrast = 33","\tDefectLength = 0.5875, DefectWidth = 0.5375, DefectContrast = 38","\tDefectLength = 0.5875, DefectWidth = 0.425, DefectContrast = 24","\tDefectLength = 0.4375, DefectWidth = 0.3125, DefectContrast = 15","\tDefectLength = 1.625, DefectWidth = 1.2625, DefectContrast = 20","\tDefectLength = 2.2, DefectWidth = 0.55, DefectContrast = 18","\tDefectLength = 0.7875, DefectWidth = 0.3875, DefectContrast = 15","\tDefectLength = 0.425, DefectWidth = 0.2375, DefectContrast = 10","\tDefectLength = 0.575, DefectWidth = 0.55, DefectContrast = 37","\tDefectLength = 0.2625, DefectWidth = 0.2625, DefectContrast = 16","\tDefectLength = 0.225, DefectWidth = 0.1625, DefectContrast = 30","\tDefectLength = 1.3125, DefectWidth = 0.2375, DefectContrast = 39","\tDefectLength = 0.175, DefectWidth = 0.1625, DefectContrast = 31","\tDefectLength = 1.8625, DefectWidth = 0.2375, DefectContrast = 35","\tDefectLength = 0.2375, DefectWidth = 0.1625, DefectContrast = 33","\tDefectLength = 3.1875, DefectWidth = 0.3125, DefectContrast = 46","\tDefectLength = 0.225, DefectWidth = 0.1625, DefectContrast = 31","\tDefectLength = 1.25, DefectWidth = 0.2375, DefectContrast = 35","\tDefectLength = 3.8, DefectWidth = 0.2875, DefectContrast = 66","\tDefectLength = 0.2, DefectWidth = 0.1625, DefectContrast = 28","\tDefectLength = 0.35, DefectWidth = 0.15, DefectContrast = 28","\tDefectLength = 0.8875, DefectWidth = 0.2125, DefectContrast = 102","\tDefectLength = 0.6, DefectWidth = 0.15, DefectContrast = 89","\tDefectLength = 0.325, DefectWidth = 0.15, DefectContrast = 90","\tDefectLength = 0.35, DefectWidth = 0.125, DefectContrast = 88","\tDefectLength = 0.3125, DefectWidth = 0.15, DefectContrast = 88","\tDefectLength = 0.2625, DefectWidth = 0.0875, DefectContrast = 91","\tDefectLength = 1.8, DefectWidth = 0.18, DefectContrast = 156","\tDefectLength = 1.8, DefectWidth = 0.08, DefectContrast = 194","\tDefectLength = 1.8, DefectWidth = 0.14, DefectContrast = 213","The defect is too big: surface is A, defect type is Scratch, defect length is 1.6125,defect width is 0.625, defect area_mm is 0.08969, defect contrast is 25","The defect is too big: surface is A, defect type is Scratch, defect length is 0.8875,defect width is 0.675, defect area_mm is 0.06672, defect contrast is 29","The defect is too big: surface is A, defect type is Scratch, defect length is 1.0125,defect width is 0.4625, defect area_mm is 0.06266, defect contrast is 22","defect count is over Scratch limitation(4)","The defect is too big: surface is A, defect type is Scratch, defect length is 1.05,defect width is 0.5, defect area_mm is 0.06922, defect contrast is 21","The defect is too big: surface is A, defect type is Scratch, defect length is 0.775,defect width is 0.65, defect area_mm is 0.05703, defect contrast is 17","The defect is too big: surface is A, defect type is Scratch, defect length is 1.025,defect width is 0.475, defect area_mm is 0.06125, defect contrast is 4","The defect is too big: surface is A, defect type is Scratch, defect length is 0.9,defect width is 0.625, defect area_mm is 0.06125, defect contrast is 5","The defect is too big: surface is A, defect type is Scratch, defect length is 1.575,defect width is 0.575, defect area_mm is 0.08688, defect contrast is 5","The defect is too big: surface is A, defect type is Scratch, defect length is 1.05,defect width is 0.5, defect area_mm is 0.06188, defect contrast is 5","The defect is too big: surface is A, defect type is Nick, defect length is 0.7375,defect width is 0.525, defect area_mm is 0.08516, defect contrast is 28","defect count is over Nick limitation(4)","The defect is too big: surface is A, defect type is Nick, defect length is 0.7875,defect width is 0.5, defect area_mm is 0.09766, defect contrast is 39","The defect is too big: surface is A, defect type is Nick, defect length is 0.725,defect width is 0.4125, defect area_mm is 0.05813, defect contrast is 16","The defect is too big: surface is A, defect type is Nick, defect length is 16.45,defect width is 2.2, defect area_mm is 9.30406, defect contrast is 9","The defect is too big: surface is A, defect type is Nick, defect length is 5.5625,defect width is 5.55, defect area_mm is 13.92375, defect contrast is 30","The defect is too big: surface is A, defect type is Nick, defect length is 2.4625,defect width is 2.2625, defect area_mm is 2.86844, defect contrast is 8","The defect is too big: surface is A, defect type is Nick, defect length is 1.225,defect width is 0.525, defect area_mm is 0.38266, defect contrast is 35","The defect is too big: surface is A, defect type is Nick, defect length is 1.2,defect width is 0.8125, defect area_mm is 0.59453, defect contrast is 34","The defect is too big: surface is A, defect type is Nick, defect length is 1.08,defect width is 0.5, defect area_mm is 0.43, defect contrast is 39","The defect is too big: surface is A, defect type is Nick, defect length is 1.24,defect width is 1.04, defect area_mm is 0.9676, defect contrast is 31","The defect is too big: surface is A, defect type is Nick, defect length is 1.36,defect width is 1.12, defect area_mm is 1.0664, defect contrast is 32","The defect is too big: surface is A, defect type is Nick, defect length is 1.4,defect width is 1.14, defect area_mm is 1.11, defect contrast is 32","The defect is too big: surface is A, defect type is Nick, defect length is 1.2,defect width is 1.14, defect area_mm is 0.708, defect contrast is 26","defect count is over Dent limitation(0)","Surface Defect Count is over limitation(4)","*****Current Grade = A, Current Surface = B*****","Defect Type Nick, Defects number = 42 on B Surface","\tDefectLength = 15.74, DefectWidth = 0.5, DefectContrast = 17","\tDefectLength = 30.32, DefectWidth = 0.54, DefectContrast = 21","\tDefectLength = 11.38, DefectWidth = 1.42, DefectContrast = 27","\tDefectLength = 14.1984, DefectWidth = 0.2592, DefectContrast = 12","\tDefectLength = 12.2016, DefectWidth = 0.1824, DefectContrast = 14","\tDefectLength = 3.8304, DefectWidth = 0.1152, DefectContrast = 7","\tDefectLength = 1.7088, DefectWidth = 1.4304, DefectContrast = 9","\tDefectLength = 0.8352, DefectWidth = 0.1344, DefectContrast = 7","\tDefectLength = 0.5184, DefectWidth = 0.3936, DefectContrast = 12","\tDefectLength = 0.3168, DefectWidth = 0.192, DefectContrast = 9","\tDefectLength = 0.624, DefectWidth = 0.1824, DefectContrast = 8","\tDefectLength = 0.672, DefectWidth = 0.3552, DefectContrast = 8","\tDefectLength = 0.4608, DefectWidth = 0.3168, DefectContrast = 10","\tDefectLength = 0.528, DefectWidth = 0.1728, DefectContrast = 8","\tDefectLength = 2.784, DefectWidth = 1.3056, DefectContrast = 7","\tDefectLength = 1.2384, DefectWidth = 0.1152, DefectContrast = 9","\tDefectLength = 11.8368, DefectWidth = 0.288, DefectContrast = 13","\tDefectLength = 0.48, DefectWidth = 0.2016, DefectContrast = 8","\tDefectLength = 1.8432, DefectWidth = 0.1344, DefectContrast = 10","\tDefectLength = 1.3152, DefectWidth = 0.2304, DefectContrast = 6","\tDefectLength = 10.1856, DefectWidth = 0.192, DefectContrast = 17","\tDefectLength = 5.3472, DefectWidth = 0.1152, DefectContrast = 8","\tDefectLength = 5.5776, DefectWidth = 0.144, DefectContrast = 8","\tDefectLength = 1.8432, DefectWidth = 0.1536, DefectContrast = 6","\tDefectLength = 0.7968, DefectWidth = 0.192, DefectContrast = 12","\tDefectLength = 3.456, DefectWidth = 0.1824, DefectContrast = 8","\tDefectLength = 1.0272, DefectWidth = 0.1152, DefectContrast = 6","\tDefectLength = 1.5456, DefectWidth = 0.1536, DefectContrast = 12","\tDefectLength = 11.8368, DefectWidth = 0.3264, DefectContrast = 11","\tDefectLength = 0.9408, DefectWidth = 0.096, DefectContrast = 7","\tDefectLength = 1.536, DefectWidth = 0.1152, DefectContrast = 7","\tDefectLength = 10.5408, DefectWidth = 0.1344, DefectContrast = 17","\tDefectLength = 2.3904, DefectWidth = 0.1248, DefectContrast = 7","\tDefectLength = 8.0352, DefectWidth = 0.2112, DefectContrast = 9","\tDefectLength = 0.5568, DefectWidth = 0.4896, DefectContrast = 6","\tDefectLength = 3.744, DefectWidth = 0.1248, DefectContrast = 7","\tDefectLength = 1.7472, DefectWidth = 0.8736, DefectContrast = 9","\tDefectLength = 0.576, DefectWidth = 0.3936, DefectContrast = 14","\tDefectLength = 11.8944, DefectWidth = 0.2496, DefectContrast = 10","\tDefectLength = 9.1776, DefectWidth = 0.1824, DefectContrast = 13","\tDefectLength = 1.9392, DefectWidth = 0.1056, DefectContrast = 5","\tDefectLength = 1.8528, DefectWidth = 0.1152, DefectContrast = 6","Defect Type Dent, Defects number = 14 on B Surface","\tDefectLength = 7.44, DefectWidth = 1.56, DefectContrast = 33","\tDefectLength = 5.26, DefectWidth = 1.24, DefectContrast = 21","\tDefectLength = 1.4304, DefectWidth = 0.1056, DefectContrast = 14","\tDefectLength = 1.104, DefectWidth = 0.1632, DefectContrast = 17","\tDefectLength = 0.2016, DefectWidth = 0.1728, DefectContrast = 21","\tDefectLength = 0.8928, DefectWidth = 0.144, DefectContrast = 27","\tDefectLength = 0.7584, DefectWidth = 0.1056, DefectContrast = 18","\tDefectLength = 0.9696, DefectWidth = 0.1056, DefectContrast = 20","\tDefectLength = 0.4224, DefectWidth = 0.096, DefectContrast = 21","\tDefectLength = 0.6336, DefectWidth = 0.0864, DefectContrast = 25","\tDefectLength = 1.6032, DefectWidth = 0.096, DefectContrast = 19","\tDefectLength = 0.2688, DefectWidth = 0.144, DefectContrast = 29","\tDefectLength = 58.6, DefectWidth = 1.48, DefectContrast = 25","\tDefectLength = 4.42, DefectWidth = 1, DefectContrast = 20","The defect is too big: surface is B, defect type is Nick, defect length is 15.74,defect width is 0.5, defect area_mm is 5.2964, defect contrast is 17","The defect is too big: surface is B, defect type is Nick, defect length is 30.32,defect width is 0.54, defect area_mm is 11.7036, defect contrast is 21","defect count is over Dent limitation(0)","Surface Defect Count is over limitation(12)","Grade max total defects are over limitation(12)."],"GradeMaxDefectTotal":[12,170],"SurfaceItems":[{"SurfaceName":"AA","SurfaceTotalCount":[1,0],"SurfaceGroup":{"max_defect_none":[-1,0],"max_defect_others":[0,0],"max_defect_others_Scratch":[0,0],"max_defect_others_Nick":[0,0],"max_defect_others_Dent":[0,0],"max_defect_others_Crack":[0,0],"max_defect_others_Discoloration":[0,0],"max_defect_others_GroupPindot":[0,0],"max_defect_others_AlignmentFailed":[0,0]},"SurfaceZone":{},"DefectItems":{"LogicAnd":{"Scratch":[[1,0]],"Nick":[[0,0]],"Dent":[[0,0]],"Crack":[[0,0]],"Discoloration":[[0,0]],"DifferentScreen":[[0,0]]},"LogicOr":{"GroupPindot":[[0,0]]}}},{"SurfaceName":"A","SurfaceTotalCount":[4,116],"SurfaceGroup":{"max_defect_none":[-1,116],"max_defect_others":[0,0],"max_defect_others_Scratch":[0,9],"max_defect_others_Nick":[0,13],"max_defect_others_Dent":[0,0],"max_defect_others_Crack":[0,0],"max_defect_others_Discoloration":[0,0],"max_defect_others_GroupPindot":[0,0],"max_defect_others_AlignmentFailed":[0,0]},"SurfaceZone":{},"DefectItems":{"LogicAnd":{"Scratch":[[4,38]],"Nick":[[4,24]],"Dent":[[0,54]],"Crack":[[0,0]],"Discoloration":[[4,0]]},"LogicOr":{"GroupPindot":[[2,0],[1,0]]}}},{"SurfaceName":"B","SurfaceTotalCount":[12,54],"SurfaceGroup":{"max_defect_nick_gcd_minor":[12,40],"max_defect_discoloration_minor":[12,0],"max_defect_none":[-1,14],"max_defect_others":[0,0],"max_defect_others_Scratch":[0,0],"max_defect_others_Nick":[0,2],"max_defect_others_Dent":[0,0],"max_defect_others_Crack":[0,0],"max_defect_others_Discoloration":[0,0],"max_defect_others_GroupPindot":[0,0],"max_defect_others_AlignmentFailed":[0,0]},"SurfaceZone":{},"DefectItems":{"LogicAnd":{"Scratch":[[12,0]],"Nick":[[-1,40]],"Dent":[[0,14]],"Crack":[[0,0]],"Discoloration":[[12,0]]},"LogicOr":{"GroupPindot":[[2,0],[1,0]]}}}]},{"GradingLevel":"B","Comment":["*****Current Grade = B, Current Surface = A*****","Defect Type Scratch, Defects number = 47 on A Surface","\tDefectLength = 1.6125, DefectWidth = 0.625, DefectContrast = 25","\tDefectLength = 1.1, DefectWidth = 0.25, DefectContrast = 34","\tDefectLength = 0.8875, DefectWidth = 0.675, DefectContrast = 29","\tDefectLength = 0.6, DefectWidth = 0.1625, DefectContrast = 21","\tDefectLength = 0.8625, DefectWidth = 0.3625, DefectContrast = 34","\tDefectLength = 1.0125, DefectWidth = 0.4625, DefectContrast = 22","\tDefectLength = 1.1, DefectWidth = 0.2625, DefectContrast = 30","\tDefectLength = 0.8375, DefectWidth = 0.1375, DefectContrast = 27","\tDefectLength = 0.5125, DefectWidth = 0.1625, DefectContrast = 19","\tDefectLength = 0.5375, DefectWidth = 0.35, DefectContrast = 19","\tDefectLength = 0.5, DefectWidth = 0.1875, DefectContrast = 37","\tDefectLength = 1.05, DefectWidth = 0.5, DefectContrast = 21","\tDefectLength = 0.4, DefectWidth = 0.375, DefectContrast = 24","\tDefectLength = 0.6, DefectWidth = 0.4125, DefectContrast = 31","\tDefectLength = 0.775, DefectWidth = 0.65, DefectContrast = 17","\tDefectLength = 0.8, DefectWidth = 0.0625, DefectContrast = 8","\tDefectLength = 0.4875, DefectWidth = 0.2875, DefectContrast = 17","\tDefectLength = 0.575, DefectWidth = 0.3125, DefectContrast = 26","\tDefectLength = 0.65, DefectWidth = 0.175, DefectContrast = 31","\tDefectLength = 0.5625, DefectWidth = 0.125, DefectContrast = 19","\tDefectLength = 1.0375, DefectWidth = 0.1375, DefectContrast = 26","\tDefectLength = 1.175, DefectWidth = 0.35, DefectContrast = 29","\tDefectLength = 0.5875, DefectWidth = 0.2625, DefectContrast = 19","\tDefectLength = 0.85, DefectWidth = 0.3125, DefectContrast = 22","\tDefectLength = 0.6125, DefectWidth = 0.2125, DefectContrast = 15","\tDefectLength = 0.8, DefectWidth = 0.3375, DefectContrast = 25","\tDefectLength = 0.5375, DefectWidth = 0.2375, DefectContrast = 13","\tDefectLength = 0.425, DefectWidth = 0.35, DefectContrast = 18","\tDefectLength = 0.6625, DefectWidth = 0.2, DefectContrast = 22","\tDefectLength = 0.65, DefectWidth = 0.15, DefectContrast = 5","\tDefectLength = 3.575, DefectWidth = 0.2, DefectContrast = 2","\tDefectLength = 0.675, DefectWidth = 0.175, DefectContrast = 3","\tDefectLength = 0.575, DefectWidth = 0.25, DefectContrast = 5","\tDefectLength = 0.4, DefectWidth = 0.375, DefectContrast = 4","\tDefectLength = 1.025, DefectWidth = 0.475, DefectContrast = 4","\tDefectLength = 0.5, DefectWidth = 0.225, DefectContrast = 3","\tDefectLength = 0.9, DefectWidth = 0.625, DefectContrast = 5","\tDefectLength = 1.1, DefectWidth = 0.2, DefectContrast = 8","\tDefectLength = 1.575, DefectWidth = 0.575, DefectContrast = 5","\tDefectLength = 1.05, DefectWidth = 0.5, DefectContrast = 5","\tDefectLength = 0.55, DefectWidth = 0.15, DefectContrast = 3","\tDefectLength = 0.9, DefectWidth = 0.3, DefectContrast = 7","\tDefectLength = 1, DefectWidth = 0.1, DefectContrast = 6","\tDefectLength = 0.5, DefectWidth = 0.15, DefectContrast = 8","\tDefectLength = 1.1, DefectWidth = 0.225, DefectContrast = 7","\tDefectLength = 0.425, DefectWidth = 0.4, DefectContrast = 3","\tDefectLength = 0.325, DefectWidth = 0.175, DefectContrast = 1","Defect Type Nick, Defects number = 37 on A Surface","\tDefectLength = 0.2875, DefectWidth = 0.15, DefectContrast = 16","\tDefectLength = 0.7375, DefectWidth = 0.525, DefectContrast = 28","\tDefectLength = 0.2625, DefectWidth = 0.1125, DefectContrast = 28","\tDefectLength = 0.5375, DefectWidth = 0.325, DefectContrast = 21","\tDefectLength = 0.3, DefectWidth = 0.1625, DefectContrast = 20","\tDefectLength = 0.2625, DefectWidth = 0.125, DefectContrast = 15","\tDefectLength = 0.3625, DefectWidth = 0.2625, DefectContrast = 15","\tDefectLength = 0.7875, DefectWidth = 0.5, DefectContrast = 39","\tDefectLength = 0.25, DefectWidth = 0.225, DefectContrast = 36","\tDefectLength = 0.5125, DefectWidth = 0.3875, DefectContrast = 14","\tDefectLength = 0.225, DefectWidth = 0.1375, DefectContrast = 19","\tDefectLength = 0.2125, DefectWidth = 0.2125, DefectContrast = 48","\tDefectLength = 0.1875, DefectWidth = 0.1875, DefectContrast = 23","\tDefectLength = 0.725, DefectWidth = 0.4125, DefectContrast = 16","\tDefectLength = 0.3, DefectWidth = 0.125, DefectContrast = 25","\tDefectLength = 0.2, DefectWidth = 0.175, DefectContrast = 29","\tDefectLength = 0.4, DefectWidth = 0.2375, DefectContrast = 10","\tDefectLength = 0.225, DefectWidth = 0.15, DefectContrast = 34","\tDefectLength = 0.2125, DefectWidth = 0.0875, DefectContrast = 29","\tDefectLength = 0.2625, DefectWidth = 0.225, DefectContrast = 19","\tDefectLength = 0.2375, DefectWidth = 0.1875, DefectContrast = 26","\tDefectLength = 0.225, DefectWidth = 0.2, DefectContrast = 22","\tDefectLength = 0.2, DefectWidth = 0.15, DefectContrast = 20","\tDefectLength = 16.45, DefectWidth = 2.2, DefectContrast = 9","\tDefectLength = 5.5625, DefectWidth = 5.55, DefectContrast = 30","\tDefectLength = 2.4625, DefectWidth = 2.2625, DefectContrast = 8","\tDefectLength = 1.225, DefectWidth = 0.525, DefectContrast = 35","\tDefectLength = 1.2, DefectWidth = 0.8125, DefectContrast = 34","\tDefectLength = 1.08, DefectWidth = 0.5, DefectContrast = 39","\tDefectLength = 1.24, DefectWidth = 1.04, DefectContrast = 31","\tDefectLength = 1.8, DefectWidth = 0.26, DefectContrast = 98","\tDefectLength = 1.8, DefectWidth = 0.34, DefectContrast = 73","\tDefectLength = 1.8, DefectWidth = 0.38, DefectContrast = 87","\tDefectLength = 0.98, DefectWidth = 0.34, DefectContrast = 41","\tDefectLength = 1.36, DefectWidth = 1.12, DefectContrast = 32","\tDefectLength = 1.4, DefectWidth = 1.14, DefectContrast = 32","\tDefectLength = 1.2, DefectWidth = 1.14, DefectContrast = 26","Defect Type Dent, Defects number = 54 on A Surface","\tDefectLength = 0.525, DefectWidth = 0.35, DefectContrast = 18","\tDefectLength = 1.1625, DefectWidth = 0.525, DefectContrast = 18","\tDefectLength = 0.45, DefectWidth = 0.3625, DefectContrast = 13","\tDefectLength = 0.65, DefectWidth = 0.3375, DefectContrast = 31","\tDefectLength = 16.825, DefectWidth = 3.2375, DefectContrast = 27","\tDefectLength = 0.35, DefectWidth = 0.3125, DefectContrast = 16","\tDefectLength = 3.75, DefectWidth = 3.75, DefectContrast = 53","\tDefectLength = 0.625, DefectWidth = 0.225, DefectContrast = 11","\tDefectLength = 1.3, DefectWidth = 0.5875, DefectContrast = 61","\tDefectLength = 0.3375, DefectWidth = 0.2875, DefectContrast = 17","\tDefectLength = 0.45, DefectWidth = 0.4375, DefectContrast = 16","\tDefectLength = 0.95, DefectWidth = 0.675, DefectContrast = 15","\tDefectLength = 20.525, DefectWidth = 4.2125, DefectContrast = 100","\tDefectLength = 2.7125, DefectWidth = 1.975, DefectContrast = 22","\tDefectLength = 7.125, DefectWidth = 1.775, DefectContrast = 34","\tDefectLength = 2.075, DefectWidth = 1.4375, DefectContrast = 17","\tDefectLength = 1.1125, DefectWidth = 0.2, DefectContrast = 20","\tDefectLength = 1.4625, DefectWidth = 0.2375, DefectContrast = 25","\tDefectLength = 1.9375, DefectWidth = 0.25, DefectContrast = 24","\tDefectLength = 0.5, DefectWidth = 0.175, DefectContrast = 24","\tDefectLength = 0.3125, DefectWidth = 0.275, DefectContrast = 14","\tDefectLength = 0.625, DefectWidth = 0.4125, DefectContrast = 16","\tDefectLength = 0.4, DefectWidth = 0.3875, DefectContrast = 35","\tDefectLength = 0.35, DefectWidth = 0.275, DefectContrast = 14","\tDefectLength = 0.575, DefectWidth = 0.5, DefectContrast = 33","\tDefectLength = 0.5875, DefectWidth = 0.5375, DefectContrast = 38","\tDefectLength = 0.5875, DefectWidth = 0.425, DefectContrast = 24","\tDefectLength = 0.4375, DefectWidth = 0.3125, DefectContrast = 15","\tDefectLength = 1.625, DefectWidth = 1.2625, DefectContrast = 20","\tDefectLength = 2.2, DefectWidth = 0.55, DefectContrast = 18","\tDefectLength = 0.7875, DefectWidth = 0.3875, DefectContrast = 15","\tDefectLength = 0.425, DefectWidth = 0.2375, DefectContrast = 10","\tDefectLength = 0.575, DefectWidth = 0.55, DefectContrast = 37","\tDefectLength = 0.2625, DefectWidth = 0.2625, DefectContrast = 16","\tDefectLength = 0.225, DefectWidth = 0.1625, DefectContrast = 30","\tDefectLength = 1.3125, DefectWidth = 0.2375, DefectContrast = 39","\tDefectLength = 0.175, DefectWidth = 0.1625, DefectContrast = 31","\tDefectLength = 1.8625, DefectWidth = 0.2375, DefectContrast = 35","\tDefectLength = 0.2375, DefectWidth = 0.1625, DefectContrast = 33","\tDefectLength = 3.1875, DefectWidth = 0.3125, DefectContrast = 46","\tDefectLength = 0.225, DefectWidth = 0.1625, DefectContrast = 31","\tDefectLength = 1.25, DefectWidth = 0.2375, DefectContrast = 35","\tDefectLength = 3.8, DefectWidth = 0.2875, DefectContrast = 66","\tDefectLength = 0.2, DefectWidth = 0.1625, DefectContrast = 28","\tDefectLength = 0.35, DefectWidth = 0.15, DefectContrast = 28","\tDefectLength = 0.8875, DefectWidth = 0.2125, DefectContrast = 102","\tDefectLength = 0.6, DefectWidth = 0.15, DefectContrast = 89","\tDefectLength = 0.325, DefectWidth = 0.15, DefectContrast = 90","\tDefectLength = 0.35, DefectWidth = 0.125, DefectContrast = 88","\tDefectLength = 0.3125, DefectWidth = 0.15, DefectContrast = 88","\tDefectLength = 0.2625, DefectWidth = 0.0875, DefectContrast = 91","\tDefectLength = 1.8, DefectWidth = 0.18, DefectContrast = 156","\tDefectLength = 1.8, DefectWidth = 0.08, DefectContrast = 194","\tDefectLength = 1.8, DefectWidth = 0.14, DefectContrast = 213","The defect is too big: surface is A, defect type is Scratch, defect length is 1.6125,defect width is 0.625, defect area_mm is 0.08969, defect contrast is 25","The defect is too big: surface is A, defect type is Scratch, defect length is 0.8875,defect width is 0.675, defect area_mm is 0.06672, defect contrast is 29","The defect is too big: surface is A, defect type is Scratch, defect length is 1.0125,defect width is 0.4625, defect area_mm is 0.06266, defect contrast is 22","defect count is over Scratch limitation(6)","The defect is too big: surface is A, defect type is Scratch, defect length is 1.05,defect width is 0.5, defect area_mm is 0.06922, defect contrast is 21","The defect is too big: surface is A, defect type is Scratch, defect length is 0.775,defect width is 0.65, defect area_mm is 0.05703, defect contrast is 17","The defect is too big: surface is A, defect type is Scratch, defect length is 1.025,defect width is 0.475, defect area_mm is 0.06125, defect contrast is 4","The defect is too big: surface is A, defect type is Scratch, defect length is 0.9,defect width is 0.625, defect area_mm is 0.06125, defect contrast is 5","The defect is too big: surface is A, defect type is Scratch, defect length is 1.575,defect width is 0.575, defect area_mm is 0.08688, defect contrast is 5","The defect is too big: surface is A, defect type is Scratch, defect length is 1.05,defect width is 0.5, defect area_mm is 0.06188, defect contrast is 5","The defect is too big: surface is A, defect type is Nick, defect length is 0.7375,defect width is 0.525, defect area_mm is 0.08516, defect contrast is 28","The defect is too big: surface is A, defect type is Nick, defect length is 0.7875,defect width is 0.5, defect area_mm is 0.09766, defect contrast is 39","defect count is over Nick limitation(6)","The defect is too big: surface is A, defect type is Nick, defect length is 0.725,defect width is 0.4125, defect area_mm is 0.05813, defect contrast is 16","The defect is too big: surface is A, defect type is Nick, defect length is 16.45,defect width is 2.2, defect area_mm is 9.30406, defect contrast is 9","The defect is too big: surface is A, defect type is Nick, defect length is 5.5625,defect width is 5.55, defect area_mm is 13.92375, defect contrast is 30","The defect is too big: surface is A, defect type is Nick, defect length is 2.4625,defect width is 2.2625, defect area_mm is 2.86844, defect contrast is 8","The defect is too big: surface is A, defect type is Nick, defect length is 1.225,defect width is 0.525, defect area_mm is 0.38266, defect contrast is 35","The defect is too big: surface is A, defect type is Nick, defect length is 1.2,defect width is 0.8125, defect area_mm is 0.59453, defect contrast is 34","The defect is too big: surface is A, defect type is Nick, defect length is 1.08,defect width is 0.5, defect area_mm is 0.43, defect contrast is 39","The defect is too big: surface is A, defect type is Nick, defect length is 1.24,defect width is 1.04, defect area_mm is 0.9676, defect contrast is 31","The defect is too big: surface is A, defect type is Nick, defect length is 1.36,defect width is 1.12, defect area_mm is 1.0664, defect contrast is 32","The defect is too big: surface is A, defect type is Nick, defect length is 1.4,defect width is 1.14, defect area_mm is 1.11, defect contrast is 32","The defect is too big: surface is A, defect type is Nick, defect length is 1.2,defect width is 1.14, defect area_mm is 0.708, defect contrast is 26","defect count is over Dent limitation(0)","Surface Defect Count is over limitation(6)","*****Current Grade = B, Current Surface = B*****","Defect Type Nick, Defects number = 42 on B Surface","\tDefectLength = 15.74, DefectWidth = 0.5, DefectContrast = 17","\tDefectLength = 30.32, DefectWidth = 0.54, DefectContrast = 21","\tDefectLength = 11.38, DefectWidth = 1.42, DefectContrast = 27","\tDefectLength = 14.1984, DefectWidth = 0.2592, DefectContrast = 12","\tDefectLength = 12.2016, DefectWidth = 0.1824, DefectContrast = 14","\tDefectLength = 3.8304, DefectWidth = 0.1152, DefectContrast = 7","\tDefectLength = 1.7088, DefectWidth = 1.4304, DefectContrast = 9","\tDefectLength = 0.8352, DefectWidth = 0.1344, DefectContrast = 7","\tDefectLength = 0.5184, DefectWidth = 0.3936, DefectContrast = 12","\tDefectLength = 0.3168, DefectWidth = 0.192, DefectContrast = 9","\tDefectLength = 0.624, DefectWidth = 0.1824, DefectContrast = 8","\tDefectLength = 0.672, DefectWidth = 0.3552, DefectContrast = 8","\tDefectLength = 0.4608, DefectWidth = 0.3168, DefectContrast = 10","\tDefectLength = 0.528, DefectWidth = 0.1728, DefectContrast = 8","\tDefectLength = 2.784, DefectWidth = 1.3056, DefectContrast = 7","\tDefectLength = 1.2384, DefectWidth = 0.1152, DefectContrast = 9","\tDefectLength = 11.8368, DefectWidth = 0.288, DefectContrast = 13","\tDefectLength = 0.48, DefectWidth = 0.2016, DefectContrast = 8","\tDefectLength = 1.8432, DefectWidth = 0.1344, DefectContrast = 10","\tDefectLength = 1.3152, DefectWidth = 0.2304, DefectContrast = 6","\tDefectLength = 10.1856, DefectWidth = 0.192, DefectContrast = 17","\tDefectLength = 5.3472, DefectWidth = 0.1152, DefectContrast = 8","\tDefectLength = 5.5776, DefectWidth = 0.144, DefectContrast = 8","\tDefectLength = 1.8432, DefectWidth = 0.1536, DefectContrast = 6","\tDefectLength = 0.7968, DefectWidth = 0.192, DefectContrast = 12","\tDefectLength = 3.456, DefectWidth = 0.1824, DefectContrast = 8","\tDefectLength = 1.0272, DefectWidth = 0.1152, DefectContrast = 6","\tDefectLength = 1.5456, DefectWidth = 0.1536, DefectContrast = 12","\tDefectLength = 11.8368, DefectWidth = 0.3264, DefectContrast = 11","\tDefectLength = 0.9408, DefectWidth = 0.096, DefectContrast = 7","\tDefectLength = 1.536, DefectWidth = 0.1152, DefectContrast = 7","\tDefectLength = 10.5408, DefectWidth = 0.1344, DefectContrast = 17","\tDefectLength = 2.3904, DefectWidth = 0.1248, DefectContrast = 7","\tDefectLength = 8.0352, DefectWidth = 0.2112, DefectContrast = 9","\tDefectLength = 0.5568, DefectWidth = 0.4896, DefectContrast = 6","\tDefectLength = 3.744, DefectWidth = 0.1248, DefectContrast = 7","\tDefectLength = 1.7472, DefectWidth = 0.8736, DefectContrast = 9","\tDefectLength = 0.576, DefectWidth = 0.3936, DefectContrast = 14","\tDefectLength = 11.8944, DefectWidth = 0.2496, DefectContrast = 10","\tDefectLength = 9.1776, DefectWidth = 0.1824, DefectContrast = 13","\tDefectLength = 1.9392, DefectWidth = 0.1056, DefectContrast = 5","\tDefectLength = 1.8528, DefectWidth = 0.1152, DefectContrast = 6","Defect Type Dent, Defects number = 14 on B Surface","\tDefectLength = 7.44, DefectWidth = 1.56, DefectContrast = 33","\tDefectLength = 5.26, DefectWidth = 1.24, DefectContrast = 21","\tDefectLength = 1.4304, DefectWidth = 0.1056, DefectContrast = 14","\tDefectLength = 1.104, DefectWidth = 0.1632, DefectContrast = 17","\tDefectLength = 0.2016, DefectWidth = 0.1728, DefectContrast = 21","\tDefectLength = 0.8928, DefectWidth = 0.144, DefectContrast = 27","\tDefectLength = 0.7584, DefectWidth = 0.1056, DefectContrast = 18","\tDefectLength = 0.9696, DefectWidth = 0.1056, DefectContrast = 20","\tDefectLength = 0.4224, DefectWidth = 0.096, DefectContrast = 21","\tDefectLength = 0.6336, DefectWidth = 0.0864, DefectContrast = 25","\tDefectLength = 1.6032, DefectWidth = 0.096, DefectContrast = 19","\tDefectLength = 0.2688, DefectWidth = 0.144, DefectContrast = 29","\tDefectLength = 58.6, DefectWidth = 1.48, DefectContrast = 25","\tDefectLength = 4.42, DefectWidth = 1, DefectContrast = 20","The defect is too big: surface is B, defect type is Nick, defect length is 30.32,defect width is 0.54, defect area_mm is 11.7036, defect contrast is 21","The defect is too big: surface is B, defect type is Nick, defect length is 11.38,defect width is 1.42, defect area_mm is 4.1172, defect contrast is 27","defect count is over Nick limitation(16)","defect count is over Nick limitation(2)","Can not matching any defect type in criteria: the defect type is Dent","Surface Defect Count is over limitation(16)","Grade max total defects are over limitation(16)."],"GradeMaxDefectTotal":[16,156],"SurfaceItems":[{"SurfaceName":"AA","SurfaceTotalCount":[6,0],"SurfaceGroup":{"max_defect_major":[1,0],"max_defect_none":[-1,0],"max_defect_others":[0,0],"max_defect_others_Scratch":[0,0],"max_defect_others_Nick":[0,0],"max_defect_others_Dent":[0,0],"max_defect_others_Crack":[0,0],"max_defect_others_Discoloration":[0,0],"max_defect_others_GroupPindot":[0,0],"max_defect_others_AlignmentFailed":[0,0]},"SurfaceZone":{"1":[3,0],"2":[3,0],"3":[3,0],"4":[3,0],"5":[3,0]},"DefectItems":{"LogicAnd":{"Scratch":[[6,0],[1,0]],"Nick":[[6,0],[1,0]],"Crack":[[0,0]],"Discoloration":[[0,0]],"DifferentScreen":[[0,0]]},"LogicOr":{"GroupPindot":[[1,0]]}}},{"SurfaceName":"A","SurfaceTotalCount":[6,116],"SurfaceGroup":{"max_defect_major":[1,0],"max_defect_none":[-1,116],"max_defect_others":[0,0],"max_defect_others_Scratch":[0,9],"max_defect_others_Nick":[0,13],"max_defect_others_Dent":[0,0],"max_defect_others_Crack":[0,0],"max_defect_others_Discoloration":[0,0],"max_defect_others_GroupPindot":[0,0],"max_defect_others_AlignmentFailed":[0,0]},"SurfaceZone":{},"DefectItems":{"LogicAnd":{"Scratch":[[6,38],[1,0]],"Nick":[[6,24],[1,0]],"Dent":[[0,54]],"Crack":[[0,0]],"Discoloration":[[6,0],[1,0]]},"LogicOr":{"GroupPindot":[[4,0],[4,0]]}}},{"SurfaceName":"B","SurfaceTotalCount":[16,40],"SurfaceGroup":{"max_defect_major":[2,3],"max_defect_scratch_s_minor":[16,0],"max_defect_nick_gcd_minor":[16,37],"max_defect_discoloration_minor":[14,0],"max_defect_none":[-1,0],"max_defect_others":[0,1],"max_defect_others_Scratch":[0,0],"max_defect_others_Nick":[0,2],"max_defect_others_Dent":[0,0],"max_defect_others_Crack":[0,0],"max_defect_others_Discoloration":[0,0],"max_defect_others_GroupPindot":[0,0],"max_defect_others_AlignmentFailed":[0,0]},"SurfaceZone":{},"DefectItems":{"LogicAnd":{"Scratch":[[16,0],[2,0]],"Nick":[[16,37],[2,3]],"Crack":[[1,0]],"Discoloration":[[16,0],[2,0],[0,0]]},"LogicOr":{"GroupPindot":[[4,0],[1,0]]}}}]},{"GradingLevel":"C","Comment":["*****Current Grade = C, Current Surface = A*****","Defect Type Scratch, Defects number = 47 on A Surface","\tDefectLength = 1.6125, DefectWidth = 0.625, DefectContrast = 25","\tDefectLength = 1.1, DefectWidth = 0.25, DefectContrast = 34","\tDefectLength = 0.8875, DefectWidth = 0.675, DefectContrast = 29","\tDefectLength = 0.6, DefectWidth = 0.1625, DefectContrast = 21","\tDefectLength = 0.8625, DefectWidth = 0.3625, DefectContrast = 34","\tDefectLength = 1.0125, DefectWidth = 0.4625, DefectContrast = 22","\tDefectLength = 1.1, DefectWidth = 0.2625, DefectContrast = 30","\tDefectLength = 0.8375, DefectWidth = 0.1375, DefectContrast = 27","\tDefectLength = 0.5125, DefectWidth = 0.1625, DefectContrast = 19","\tDefectLength = 0.5375, DefectWidth = 0.35, DefectContrast = 19","\tDefectLength = 0.5, DefectWidth = 0.1875, DefectContrast = 37","\tDefectLength = 1.05, DefectWidth = 0.5, DefectContrast = 21","\tDefectLength = 0.4, DefectWidth = 0.375, DefectContrast = 24","\tDefectLength = 0.6, DefectWidth = 0.4125, DefectContrast = 31","\tDefectLength = 0.775, DefectWidth = 0.65, DefectContrast = 17","\tDefectLength = 0.8, DefectWidth = 0.0625, DefectContrast = 8","\tDefectLength = 0.4875, DefectWidth = 0.2875, DefectContrast = 17","\tDefectLength = 0.575, DefectWidth = 0.3125, DefectContrast = 26","\tDefectLength = 0.65, DefectWidth = 0.175, DefectContrast = 31","\tDefectLength = 0.5625, DefectWidth = 0.125, DefectContrast = 19","\tDefectLength = 1.0375, DefectWidth = 0.1375, DefectContrast = 26","\tDefectLength = 1.175, DefectWidth = 0.35, DefectContrast = 29","\tDefectLength = 0.5875, DefectWidth = 0.2625, DefectContrast = 19","\tDefectLength = 0.85, DefectWidth = 0.3125, DefectContrast = 22","\tDefectLength = 0.6125, DefectWidth = 0.2125, DefectContrast = 15","\tDefectLength = 0.8, DefectWidth = 0.3375, DefectContrast = 25","\tDefectLength = 0.5375, DefectWidth = 0.2375, DefectContrast = 13","\tDefectLength = 0.425, DefectWidth = 0.35, DefectContrast = 18","\tDefectLength = 0.6625, DefectWidth = 0.2, DefectContrast = 22","\tDefectLength = 0.65, DefectWidth = 0.15, DefectContrast = 5","\tDefectLength = 3.575, DefectWidth = 0.2, DefectContrast = 2","\tDefectLength = 0.675, DefectWidth = 0.175, DefectContrast = 3","\tDefectLength = 0.575, DefectWidth = 0.25, DefectContrast = 5","\tDefectLength = 0.4, DefectWidth = 0.375, DefectContrast = 4","\tDefectLength = 1.025, DefectWidth = 0.475, DefectContrast = 4","\tDefectLength = 0.5, DefectWidth = 0.225, DefectContrast = 3","\tDefectLength = 0.9, DefectWidth = 0.625, DefectContrast = 5","\tDefectLength = 1.1, DefectWidth = 0.2, DefectContrast = 8","\tDefectLength = 1.575, DefectWidth = 0.575, DefectContrast = 5","\tDefectLength = 1.05, DefectWidth = 0.5, DefectContrast = 5","\tDefectLength = 0.55, DefectWidth = 0.15, DefectContrast = 3","\tDefectLength = 0.9, DefectWidth = 0.3, DefectContrast = 7","\tDefectLength = 1, DefectWidth = 0.1, DefectContrast = 6","\tDefectLength = 0.5, DefectWidth = 0.15, DefectContrast = 8","\tDefectLength = 1.1, DefectWidth = 0.225, DefectContrast = 7","\tDefectLength = 0.425, DefectWidth = 0.4, DefectContrast = 3","\tDefectLength = 0.325, DefectWidth = 0.175, DefectContrast = 1","Defect Type Nick, Defects number = 37 on A Surface","\tDefectLength = 0.2875, DefectWidth = 0.15, DefectContrast = 16","\tDefectLength = 0.7375, DefectWidth = 0.525, DefectContrast = 28","\tDefectLength = 0.2625, DefectWidth = 0.1125, DefectContrast = 28","\tDefectLength = 0.5375, DefectWidth = 0.325, DefectContrast = 21","\tDefectLength = 0.3, DefectWidth = 0.1625, DefectContrast = 20","\tDefectLength = 0.2625, DefectWidth = 0.125, DefectContrast = 15","\tDefectLength = 0.3625, DefectWidth = 0.2625, DefectContrast = 15","\tDefectLength = 0.7875, DefectWidth = 0.5, DefectContrast = 39","\tDefectLength = 0.25, DefectWidth = 0.225, DefectContrast = 36","\tDefectLength = 0.5125, DefectWidth = 0.3875, DefectContrast = 14","\tDefectLength = 0.225, DefectWidth = 0.1375, DefectContrast = 19","\tDefectLength = 0.2125, DefectWidth = 0.2125, DefectContrast = 48","\tDefectLength = 0.1875, DefectWidth = 0.1875, DefectContrast = 23","\tDefectLength = 0.725, DefectWidth = 0.4125, DefectContrast = 16","\tDefectLength = 0.3, DefectWidth = 0.125, DefectContrast = 25","\tDefectLength = 0.2, DefectWidth = 0.175, DefectContrast = 29","\tDefectLength = 0.4, DefectWidth = 0.2375, DefectContrast = 10","\tDefectLength = 0.225, DefectWidth = 0.15, DefectContrast = 34","\tDefectLength = 0.2125, DefectWidth = 0.0875, DefectContrast = 29","\tDefectLength = 0.2625, DefectWidth = 0.225, DefectContrast = 19","\tDefectLength = 0.2375, DefectWidth = 0.1875, DefectContrast = 26","\tDefectLength = 0.225, DefectWidth = 0.2, DefectContrast = 22","\tDefectLength = 0.2, DefectWidth = 0.15, DefectContrast = 20","\tDefectLength = 16.45, DefectWidth = 2.2, DefectContrast = 9","\tDefectLength = 5.5625, DefectWidth = 5.55, DefectContrast = 30","\tDefectLength = 2.4625, DefectWidth = 2.2625, DefectContrast = 8","\tDefectLength = 1.225, DefectWidth = 0.525, DefectContrast = 35","\tDefectLength = 1.2, DefectWidth = 0.8125, DefectContrast = 34","\tDefectLength = 1.08, DefectWidth = 0.5, DefectContrast = 39","\tDefectLength = 1.24, DefectWidth = 1.04, DefectContrast = 31","\tDefectLength = 1.8, DefectWidth = 0.26, DefectContrast = 98","\tDefectLength = 1.8, DefectWidth = 0.34, DefectContrast = 73","\tDefectLength = 1.8, DefectWidth = 0.38, DefectContrast = 87","\tDefectLength = 0.98, DefectWidth = 0.34, DefectContrast = 41","\tDefectLength = 1.36, DefectWidth = 1.12, DefectContrast = 32","\tDefectLength = 1.4, DefectWidth = 1.14, DefectContrast = 32","\tDefectLength = 1.2, DefectWidth = 1.14, DefectContrast = 26","Defect Type Dent, Defects number = 54 on A Surface","\tDefectLength = 0.525, DefectWidth = 0.35, DefectContrast = 18","\tDefectLength = 1.1625, DefectWidth = 0.525, DefectContrast = 18","\tDefectLength = 0.45, DefectWidth = 0.3625, DefectContrast = 13","\tDefectLength = 0.65, DefectWidth = 0.3375, DefectContrast = 31","\tDefectLength = 16.825, DefectWidth = 3.2375, DefectContrast = 27","\tDefectLength = 0.35, DefectWidth = 0.3125, DefectContrast = 16","\tDefectLength = 3.75, DefectWidth = 3.75, DefectContrast = 53","\tDefectLength = 0.625, DefectWidth = 0.225, DefectContrast = 11","\tDefectLength = 1.3, DefectWidth = 0.5875, DefectContrast = 61","\tDefectLength = 0.3375, DefectWidth = 0.2875, DefectContrast = 17","\tDefectLength = 0.45, DefectWidth = 0.4375, DefectContrast = 16","\tDefectLength = 0.95, DefectWidth = 0.675, DefectContrast = 15","\tDefectLength = 20.525, DefectWidth = 4.2125, DefectContrast = 100","\tDefectLength = 2.7125, DefectWidth = 1.975, DefectContrast = 22","\tDefectLength = 7.125, DefectWidth = 1.775, DefectContrast = 34","\tDefectLength = 2.075, DefectWidth = 1.4375, DefectContrast = 17","\tDefectLength = 1.1125, DefectWidth = 0.2, DefectContrast = 20","\tDefectLength = 1.4625, DefectWidth = 0.2375, DefectContrast = 25","\tDefectLength = 1.9375, DefectWidth = 0.25, DefectContrast = 24","\tDefectLength = 0.5, DefectWidth = 0.175, DefectContrast = 24","\tDefectLength = 0.3125, DefectWidth = 0.275, DefectContrast = 14","\tDefectLength = 0.625, DefectWidth = 0.4125, DefectContrast = 16","\tDefectLength = 0.4, DefectWidth = 0.3875, DefectContrast = 35","\tDefectLength = 0.35, DefectWidth = 0.275, DefectContrast = 14","\tDefectLength = 0.575, DefectWidth = 0.5, DefectContrast = 33","\tDefectLength = 0.5875, DefectWidth = 0.5375, DefectContrast = 38","\tDefectLength = 0.5875, DefectWidth = 0.425, DefectContrast = 24","\tDefectLength = 0.4375, DefectWidth = 0.3125, DefectContrast = 15","\tDefectLength = 1.625, DefectWidth = 1.2625, DefectContrast = 20","\tDefectLength = 2.2, DefectWidth = 0.55, DefectContrast = 18","\tDefectLength = 0.7875, DefectWidth = 0.3875, DefectContrast = 15","\tDefectLength = 0.425, DefectWidth = 0.2375, DefectContrast = 10","\tDefectLength = 0.575, DefectWidth = 0.55, DefectContrast = 37","\tDefectLength = 0.2625, DefectWidth = 0.2625, DefectContrast = 16","\tDefectLength = 0.225, DefectWidth = 0.1625, DefectContrast = 30","\tDefectLength = 1.3125, DefectWidth = 0.2375, DefectContrast = 39","\tDefectLength = 0.175, DefectWidth = 0.1625, DefectContrast = 31","\tDefectLength = 1.8625, DefectWidth = 0.2375, DefectContrast = 35","\tDefectLength = 0.2375, DefectWidth = 0.1625, DefectContrast = 33","\tDefectLength = 3.1875, DefectWidth = 0.3125, DefectContrast = 46","\tDefectLength = 0.225, DefectWidth = 0.1625, DefectContrast = 31","\tDefectLength = 1.25, DefectWidth = 0.2375, DefectContrast = 35","\tDefectLength = 3.8, DefectWidth = 0.2875, DefectContrast = 66","\tDefectLength = 0.2, DefectWidth = 0.1625, DefectContrast = 28","\tDefectLength = 0.35, DefectWidth = 0.15, DefectContrast = 28","\tDefectLength = 0.8875, DefectWidth = 0.2125, DefectContrast = 102","\tDefectLength = 0.6, DefectWidth = 0.15, DefectContrast = 89","\tDefectLength = 0.325, DefectWidth = 0.15, DefectContrast = 90","\tDefectLength = 0.35, DefectWidth = 0.125, DefectContrast = 88","\tDefectLength = 0.3125, DefectWidth = 0.15, DefectContrast = 88","\tDefectLength = 0.2625, DefectWidth = 0.0875, DefectContrast = 91","\tDefectLength = 1.8, DefectWidth = 0.18, DefectContrast = 156","\tDefectLength = 1.8, DefectWidth = 0.08, DefectContrast = 194","\tDefectLength = 1.8, DefectWidth = 0.14, DefectContrast = 213","The defect is too big: surface is A, defect type is Scratch, defect length is 1.6125,defect width is 0.625, defect area_mm is 0.08969, defect contrast is 25","The defect is too big: surface is A, defect type is Scratch, defect length is 0.8875,defect width is 0.675, defect area_mm is 0.06672, defect contrast is 29","The defect is too big: surface is A, defect type is Scratch, defect length is 1.0125,defect width is 0.4625, defect area_mm is 0.06266, defect contrast is 22","The defect is too big: surface is A, defect type is Scratch, defect length is 1.05,defect width is 0.5, defect area_mm is 0.06922, defect contrast is 21","defect count is over Scratch limitation(8)","The defect is too big: surface is A, defect type is Scratch, defect length is 0.775,defect width is 0.65, defect area_mm is 0.05703, defect contrast is 17","The defect is too big: surface is A, defect type is Scratch, defect length is 1.025,defect width is 0.475, defect area_mm is 0.06125, defect contrast is 4","The defect is too big: surface is A, defect type is Scratch, defect length is 0.9,defect width is 0.625, defect area_mm is 0.06125, defect contrast is 5","The defect is too big: surface is A, defect type is Scratch, defect length is 1.575,defect width is 0.575, defect area_mm is 0.08688, defect contrast is 5","The defect is too big: surface is A, defect type is Scratch, defect length is 1.05,defect width is 0.5, defect area_mm is 0.06188, defect contrast is 5","The defect is too big: surface is A, defect type is Nick, defect length is 0.7375,defect width is 0.525, defect area_mm is 0.08516, defect contrast is 28","The defect is too big: surface is A, defect type is Nick, defect length is 0.7875,defect width is 0.5, defect area_mm is 0.09766, defect contrast is 39","defect count is over Nick limitation(8)","The defect is too big: surface is A, defect type is Nick, defect length is 0.725,defect width is 0.4125, defect area_mm is 0.05813, defect contrast is 16","The defect is too big: surface is A, defect type is Nick, defect length is 16.45,defect width is 2.2, defect area_mm is 9.30406, defect contrast is 9","The defect is too big: surface is A, defect type is Nick, defect length is 5.5625,defect width is 5.55, defect area_mm is 13.92375, defect contrast is 30","The defect is too big: surface is A, defect type is Nick, defect length is 2.4625,defect width is 2.2625, defect area_mm is 2.86844, defect contrast is 8","The defect is too big: surface is A, defect type is Nick, defect length is 1.225,defect width is 0.525, defect area_mm is 0.38266, defect contrast is 35","The defect is too big: surface is A, defect type is Nick, defect length is 1.2,defect width is 0.8125, defect area_mm is 0.59453, defect contrast is 34","The defect is too big: surface is A, defect type is Nick, defect length is 1.08,defect width is 0.5, defect area_mm is 0.43, defect contrast is 39","The defect is too big: surface is A, defect type is Nick, defect length is 1.24,defect width is 1.04, defect area_mm is 0.9676, defect contrast is 31","The defect is too big: surface is A, defect type is Nick, defect length is 1.36,defect width is 1.12, defect area_mm is 1.0664, defect contrast is 32","The defect is too big: surface is A, defect type is Nick, defect length is 1.4,defect width is 1.14, defect area_mm is 1.11, defect contrast is 32","The defect is too big: surface is A, defect type is Nick, defect length is 1.2,defect width is 1.14, defect area_mm is 0.708, defect contrast is 26","Can not matching any defect type in criteria: the defect type is Dent","Surface Defect Count is over limitation(8)","*****Current Grade = C, Current Surface = B*****","Defect Type Nick, Defects number = 42 on B Surface","\tDefectLength = 15.74, DefectWidth = 0.5, DefectContrast = 17","\tDefectLength = 30.32, DefectWidth = 0.54, DefectContrast = 21","\tDefectLength = 11.38, DefectWidth = 1.42, DefectContrast = 27","\tDefectLength = 14.1984, DefectWidth = 0.2592, DefectContrast = 12","\tDefectLength = 12.2016, DefectWidth = 0.1824, DefectContrast = 14","\tDefectLength = 3.8304, DefectWidth = 0.1152, DefectContrast = 7","\tDefectLength = 1.7088, DefectWidth = 1.4304, DefectContrast = 9","\tDefectLength = 0.8352, DefectWidth = 0.1344, DefectContrast = 7","\tDefectLength = 0.5184, DefectWidth = 0.3936, DefectContrast = 12","\tDefectLength = 0.3168, DefectWidth = 0.192, DefectContrast = 9","\tDefectLength = 0.624, DefectWidth = 0.1824, DefectContrast = 8","\tDefectLength = 0.672, DefectWidth = 0.3552, DefectContrast = 8","\tDefectLength = 0.4608, DefectWidth = 0.3168, DefectContrast = 10","\tDefectLength = 0.528, DefectWidth = 0.1728, DefectContrast = 8","\tDefectLength = 2.784, DefectWidth = 1.3056, DefectContrast = 7","\tDefectLength = 1.2384, DefectWidth = 0.1152, DefectContrast = 9","\tDefectLength = 11.8368, DefectWidth = 0.288, DefectContrast = 13","\tDefectLength = 0.48, DefectWidth = 0.2016, DefectContrast = 8","\tDefectLength = 1.8432, DefectWidth = 0.1344, DefectContrast = 10","\tDefectLength = 1.3152, DefectWidth = 0.2304, DefectContrast = 6","\tDefectLength = 10.1856, DefectWidth = 0.192, DefectContrast = 17","\tDefectLength = 5.3472, DefectWidth = 0.1152, DefectContrast = 8","\tDefectLength = 5.5776, DefectWidth = 0.144, DefectContrast = 8","\tDefectLength = 1.8432, DefectWidth = 0.1536, DefectContrast = 6","\tDefectLength = 0.7968, DefectWidth = 0.192, DefectContrast = 12","\tDefectLength = 3.456, DefectWidth = 0.1824, DefectContrast = 8","\tDefectLength = 1.0272, DefectWidth = 0.1152, DefectContrast = 6","\tDefectLength = 1.5456, DefectWidth = 0.1536, DefectContrast = 12","\tDefectLength = 11.8368, DefectWidth = 0.3264, DefectContrast = 11","\tDefectLength = 0.9408, DefectWidth = 0.096, DefectContrast = 7","\tDefectLength = 1.536, DefectWidth = 0.1152, DefectContrast = 7","\tDefectLength = 10.5408, DefectWidth = 0.1344, DefectContrast = 17","\tDefectLength = 2.3904, DefectWidth = 0.1248, DefectContrast = 7","\tDefectLength = 8.0352, DefectWidth = 0.2112, DefectContrast = 9","\tDefectLength = 0.5568, DefectWidth = 0.4896, DefectContrast = 6","\tDefectLength = 3.744, DefectWidth = 0.1248, DefectContrast = 7","\tDefectLength = 1.7472, DefectWidth = 0.8736, DefectContrast = 9","\tDefectLength = 0.576, DefectWidth = 0.3936, DefectContrast = 14","\tDefectLength = 11.8944, DefectWidth = 0.2496, DefectContrast = 10","\tDefectLength = 9.1776, DefectWidth = 0.1824, DefectContrast = 13","\tDefectLength = 1.9392, DefectWidth = 0.1056, DefectContrast = 5","\tDefectLength = 1.8528, DefectWidth = 0.1152, DefectContrast = 6","Defect Type Dent, Defects number = 14 on B Surface","\tDefectLength = 7.44, DefectWidth = 1.56, DefectContrast = 33","\tDefectLength = 5.26, DefectWidth = 1.24, DefectContrast = 21","\tDefectLength = 1.4304, DefectWidth = 0.1056, DefectContrast = 14","\tDefectLength = 1.104, DefectWidth = 0.1632, DefectContrast = 17","\tDefectLength = 0.2016, DefectWidth = 0.1728, DefectContrast = 21","\tDefectLength = 0.8928, DefectWidth = 0.144, DefectContrast = 27","\tDefectLength = 0.7584, DefectWidth = 0.1056, DefectContrast = 18","\tDefectLength = 0.9696, DefectWidth = 0.1056, DefectContrast = 20","\tDefectLength = 0.4224, DefectWidth = 0.096, DefectContrast = 21","\tDefectLength = 0.6336, DefectWidth = 0.0864, DefectContrast = 25","\tDefectLength = 1.6032, DefectWidth = 0.096, DefectContrast = 19","\tDefectLength = 0.2688, DefectWidth = 0.144, DefectContrast = 29","\tDefectLength = 58.6, DefectWidth = 1.48, DefectContrast = 25","\tDefectLength = 4.42, DefectWidth = 1, DefectContrast = 20","defect count is over Nick limitation(3)","defect count is over Nick limitation(18)","Surface Defect Count is over limitation(18)","Grade max total defects are over limitation(26)."],"GradeMaxDefectTotal":[26,118],"SurfaceItems":[{"SurfaceName":"AA","SurfaceTotalCount":[18,0],"SurfaceGroup":{"max_defect_major":[1,0],"max_defect_none":[-1,0],"max_defect_others":[0,0],"max_defect_others_Scratch":[0,0],"max_defect_others_Nick":[0,0],"max_defect_others_Dent":[0,0],"max_defect_others_Crack":[0,0],"max_defect_others_Discoloration":[0,0],"max_defect_others_GroupPindot":[0,0],"max_defect_others_AlignmentFailed":[0,0]},"SurfaceZone":{"1":[6,0],"2":[6,0],"3":[6,0],"4":[6,0],"5":[6,0]},"DefectItems":{"LogicAnd":{"Scratch":[[18,0],[1,0]],"Nick":[[18,0],[1,0]],"Crack":[[0,0]],"Discoloration":[[-1,0]],"DifferentScreen":[[0,0]]},"LogicOr":{"GroupPindot":[[-1,0]]}}},{"SurfaceName":"A","SurfaceTotalCount":[8,62],"SurfaceGroup":{"max_defect_major":[1,0],"max_defect_nick_minor":[8,24],"max_defect_discoloration_minor":[8,0],"max_defect_none":[-1,38],"max_defect_others":[0,1],"max_defect_others_Scratch":[0,9],"max_defect_others_Nick":[0,13],"max_defect_others_Dent":[0,0],"max_defect_others_Crack":[0,0],"max_defect_others_Discoloration":[0,0],"max_defect_others_GroupPindot":[0,0],"max_defect_others_AlignmentFailed":[0,0]},"SurfaceZone":{},"DefectItems":{"LogicAnd":{"Scratch":[[8,38],[1,0]],"Nick":[[8,24],[1,0]],"Crack":[[0,0]],"Discoloration":[[8,0],[1,0],[0,0],[-1,0],[-1,0]]},"LogicOr":{"GroupPindot":[[-1,0]]}}},{"SurfaceName":"B","SurfaceTotalCount":[18,56],"SurfaceGroup":{"max_defect_major":[3,5],"max_defect_Scratch_B_Minor":[18,0],"max_defect_Nick-B-Minor":[18,37],"max_defect_none":[-1,14],"max_defect_others":[0,0],"max_defect_others_Scratch":[0,0],"max_defect_others_Nick":[0,0],"max_defect_others_Dent":[0,0],"max_defect_others_Crack":[0,0],"max_defect_others_Discoloration":[0,0],"max_defect_others_GroupPindot":[0,0],"max_defect_others_AlignmentFailed":[0,0]},"SurfaceZone":{},"DefectItems":{"LogicAnd":{"Scratch":[[18,0],[3,0]],"Nick":[[18,37],[3,5]],"Dent":[[-1,14]],"Crack":[[2,0]],"Discoloration":[[-1,0]]},"LogicOr":{"GroupPindot":[[-1,0]]}}}]},{"GradingLevel":"D+","Comment":["*****Current Grade = D+, Current Surface = A*****","Defect Type Scratch, Defects number = 47 on A Surface","\tDefectLength = 1.6125, DefectWidth = 0.625, DefectContrast = 25","\tDefectLength = 1.1, DefectWidth = 0.25, DefectContrast = 34","\tDefectLength = 0.8875, DefectWidth = 0.675, DefectContrast = 29","\tDefectLength = 0.6, DefectWidth = 0.1625, DefectContrast = 21","\tDefectLength = 0.8625, DefectWidth = 0.3625, DefectContrast = 34","\tDefectLength = 1.0125, DefectWidth = 0.4625, DefectContrast = 22","\tDefectLength = 1.1, DefectWidth = 0.2625, DefectContrast = 30","\tDefectLength = 0.8375, DefectWidth = 0.1375, DefectContrast = 27","\tDefectLength = 0.5125, DefectWidth = 0.1625, DefectContrast = 19","\tDefectLength = 0.5375, DefectWidth = 0.35, DefectContrast = 19","\tDefectLength = 0.5, DefectWidth = 0.1875, DefectContrast = 37","\tDefectLength = 1.05, DefectWidth = 0.5, DefectContrast = 21","\tDefectLength = 0.4, DefectWidth = 0.375, DefectContrast = 24","\tDefectLength = 0.6, DefectWidth = 0.4125, DefectContrast = 31","\tDefectLength = 0.775, DefectWidth = 0.65, DefectContrast = 17","\tDefectLength = 0.8, DefectWidth = 0.0625, DefectContrast = 8","\tDefectLength = 0.4875, DefectWidth = 0.2875, DefectContrast = 17","\tDefectLength = 0.575, DefectWidth = 0.3125, DefectContrast = 26","\tDefectLength = 0.65, DefectWidth = 0.175, DefectContrast = 31","\tDefectLength = 0.5625, DefectWidth = 0.125, DefectContrast = 19","\tDefectLength = 1.0375, DefectWidth = 0.1375, DefectContrast = 26","\tDefectLength = 1.175, DefectWidth = 0.35, DefectContrast = 29","\tDefectLength = 0.5875, DefectWidth = 0.2625, DefectContrast = 19","\tDefectLength = 0.85, DefectWidth = 0.3125, DefectContrast = 22","\tDefectLength = 0.6125, DefectWidth = 0.2125, DefectContrast = 15","\tDefectLength = 0.8, DefectWidth = 0.3375, DefectContrast = 25","\tDefectLength = 0.5375, DefectWidth = 0.2375, DefectContrast = 13","\tDefectLength = 0.425, DefectWidth = 0.35, DefectContrast = 18","\tDefectLength = 0.6625, DefectWidth = 0.2, DefectContrast = 22","\tDefectLength = 0.65, DefectWidth = 0.15, DefectContrast = 5","\tDefectLength = 3.575, DefectWidth = 0.2, DefectContrast = 2","\tDefectLength = 0.675, DefectWidth = 0.175, DefectContrast = 3","\tDefectLength = 0.575, DefectWidth = 0.25, DefectContrast = 5","\tDefectLength = 0.4, DefectWidth = 0.375, DefectContrast = 4","\tDefectLength = 1.025, DefectWidth = 0.475, DefectContrast = 4","\tDefectLength = 0.5, DefectWidth = 0.225, DefectContrast = 3","\tDefectLength = 0.9, DefectWidth = 0.625, DefectContrast = 5","\tDefectLength = 1.1, DefectWidth = 0.2, DefectContrast = 8","\tDefectLength = 1.575, DefectWidth = 0.575, DefectContrast = 5","\tDefectLength = 1.05, DefectWidth = 0.5, DefectContrast = 5","\tDefectLength = 0.55, DefectWidth = 0.15, DefectContrast = 3","\tDefectLength = 0.9, DefectWidth = 0.3, DefectContrast = 7","\tDefectLength = 1, DefectWidth = 0.1, DefectContrast = 6","\tDefectLength = 0.5, DefectWidth = 0.15, DefectContrast = 8","\tDefectLength = 1.1, DefectWidth = 0.225, DefectContrast = 7","\tDefectLength = 0.425, DefectWidth = 0.4, DefectContrast = 3","\tDefectLength = 0.325, DefectWidth = 0.175, DefectContrast = 1","Defect Type Nick, Defects number = 37 on A Surface","\tDefectLength = 0.2875, DefectWidth = 0.15, DefectContrast = 16","\tDefectLength = 0.7375, DefectWidth = 0.525, DefectContrast = 28","\tDefectLength = 0.2625, DefectWidth = 0.1125, DefectContrast = 28","\tDefectLength = 0.5375, DefectWidth = 0.325, DefectContrast = 21","\tDefectLength = 0.3, DefectWidth = 0.1625, DefectContrast = 20","\tDefectLength = 0.2625, DefectWidth = 0.125, DefectContrast = 15","\tDefectLength = 0.3625, DefectWidth = 0.2625, DefectContrast = 15","\tDefectLength = 0.7875, DefectWidth = 0.5, DefectContrast = 39","\tDefectLength = 0.25, DefectWidth = 0.225, DefectContrast = 36","\tDefectLength = 0.5125, DefectWidth = 0.3875, DefectContrast = 14","\tDefectLength = 0.225, DefectWidth = 0.1375, DefectContrast = 19","\tDefectLength = 0.2125, DefectWidth = 0.2125, DefectContrast = 48","\tDefectLength = 0.1875, DefectWidth = 0.1875, DefectContrast = 23","\tDefectLength = 0.725, DefectWidth = 0.4125, DefectContrast = 16","\tDefectLength = 0.3, DefectWidth = 0.125, DefectContrast = 25","\tDefectLength = 0.2, DefectWidth = 0.175, DefectContrast = 29","\tDefectLength = 0.4, DefectWidth = 0.2375, DefectContrast = 10","\tDefectLength = 0.225, DefectWidth = 0.15, DefectContrast = 34","\tDefectLength = 0.2125, DefectWidth = 0.0875, DefectContrast = 29","\tDefectLength = 0.2625, DefectWidth = 0.225, DefectContrast = 19","\tDefectLength = 0.2375, DefectWidth = 0.1875, DefectContrast = 26","\tDefectLength = 0.225, DefectWidth = 0.2, DefectContrast = 22","\tDefectLength = 0.2, DefectWidth = 0.15, DefectContrast = 20","\tDefectLength = 16.45, DefectWidth = 2.2, DefectContrast = 9","\tDefectLength = 5.5625, DefectWidth = 5.55, DefectContrast = 30","\tDefectLength = 2.4625, DefectWidth = 2.2625, DefectContrast = 8","\tDefectLength = 1.225, DefectWidth = 0.525, DefectContrast = 35","\tDefectLength = 1.2, DefectWidth = 0.8125, DefectContrast = 34","\tDefectLength = 1.08, DefectWidth = 0.5, DefectContrast = 39","\tDefectLength = 1.24, DefectWidth = 1.04, DefectContrast = 31","\tDefectLength = 1.8, DefectWidth = 0.26, DefectContrast = 98","\tDefectLength = 1.8, DefectWidth = 0.34, DefectContrast = 73","\tDefectLength = 1.8, DefectWidth = 0.38, DefectContrast = 87","\tDefectLength = 0.98, DefectWidth = 0.34, DefectContrast = 41","\tDefectLength = 1.36, DefectWidth = 1.12, DefectContrast = 32","\tDefectLength = 1.4, DefectWidth = 1.14, DefectContrast = 32","\tDefectLength = 1.2, DefectWidth = 1.14, DefectContrast = 26","Defect Type Dent, Defects number = 54 on A Surface","\tDefectLength = 0.525, DefectWidth = 0.35, DefectContrast = 18","\tDefectLength = 1.1625, DefectWidth = 0.525, DefectContrast = 18","\tDefectLength = 0.45, DefectWidth = 0.3625, DefectContrast = 13","\tDefectLength = 0.65, DefectWidth = 0.3375, DefectContrast = 31","\tDefectLength = 16.825, DefectWidth = 3.2375, DefectContrast = 27","\tDefectLength = 0.35, DefectWidth = 0.3125, DefectContrast = 16","\tDefectLength = 3.75, DefectWidth = 3.75, DefectContrast = 53","\tDefectLength = 0.625, DefectWidth = 0.225, DefectContrast = 11","\tDefectLength = 1.3, DefectWidth = 0.5875, DefectContrast = 61","\tDefectLength = 0.3375, DefectWidth = 0.2875, DefectContrast = 17","\tDefectLength = 0.45, DefectWidth = 0.4375, DefectContrast = 16","\tDefectLength = 0.95, DefectWidth = 0.675, DefectContrast = 15","\tDefectLength = 20.525, DefectWidth = 4.2125, DefectContrast = 100","\tDefectLength = 2.7125, DefectWidth = 1.975, DefectContrast = 22","\tDefectLength = 7.125, DefectWidth = 1.775, DefectContrast = 34","\tDefectLength = 2.075, DefectWidth = 1.4375, DefectContrast = 17","\tDefectLength = 1.1125, DefectWidth = 0.2, DefectContrast = 20","\tDefectLength = 1.4625, DefectWidth = 0.2375, DefectContrast = 25","\tDefectLength = 1.9375, DefectWidth = 0.25, DefectContrast = 24","\tDefectLength = 0.5, DefectWidth = 0.175, DefectContrast = 24","\tDefectLength = 0.3125, DefectWidth = 0.275, DefectContrast = 14","\tDefectLength = 0.625, DefectWidth = 0.4125, DefectContrast = 16","\tDefectLength = 0.4, DefectWidth = 0.3875, DefectContrast = 35","\tDefectLength = 0.35, DefectWidth = 0.275, DefectContrast = 14","\tDefectLength = 0.575, DefectWidth = 0.5, DefectContrast = 33","\tDefectLength = 0.5875, DefectWidth = 0.5375, DefectContrast = 38","\tDefectLength = 0.5875, DefectWidth = 0.425, DefectContrast = 24","\tDefectLength = 0.4375, DefectWidth = 0.3125, DefectContrast = 15","\tDefectLength = 1.625, DefectWidth = 1.2625, DefectContrast = 20","\tDefectLength = 2.2, DefectWidth = 0.55, DefectContrast = 18","\tDefectLength = 0.7875, DefectWidth = 0.3875, DefectContrast = 15","\tDefectLength = 0.425, DefectWidth = 0.2375, DefectContrast = 10","\tDefectLength = 0.575, DefectWidth = 0.55, DefectContrast = 37","\tDefectLength = 0.2625, DefectWidth = 0.2625, DefectContrast = 16","\tDefectLength = 0.225, DefectWidth = 0.1625, DefectContrast = 30","\tDefectLength = 1.3125, DefectWidth = 0.2375, DefectContrast = 39","\tDefectLength = 0.175, DefectWidth = 0.1625, DefectContrast = 31","\tDefectLength = 1.8625, DefectWidth = 0.2375, DefectContrast = 35","\tDefectLength = 0.2375, DefectWidth = 0.1625, DefectContrast = 33","\tDefectLength = 3.1875, DefectWidth = 0.3125, DefectContrast = 46","\tDefectLength = 0.225, DefectWidth = 0.1625, DefectContrast = 31","\tDefectLength = 1.25, DefectWidth = 0.2375, DefectContrast = 35","\tDefectLength = 3.8, DefectWidth = 0.2875, DefectContrast = 66","\tDefectLength = 0.2, DefectWidth = 0.1625, DefectContrast = 28","\tDefectLength = 0.35, DefectWidth = 0.15, DefectContrast = 28","\tDefectLength = 0.8875, DefectWidth = 0.2125, DefectContrast = 102","\tDefectLength = 0.6, DefectWidth = 0.15, DefectContrast = 89","\tDefectLength = 0.325, DefectWidth = 0.15, DefectContrast = 90","\tDefectLength = 0.35, DefectWidth = 0.125, DefectContrast = 88","\tDefectLength = 0.3125, DefectWidth = 0.15, DefectContrast = 88","\tDefectLength = 0.2625, DefectWidth = 0.0875, DefectContrast = 91","\tDefectLength = 1.8, DefectWidth = 0.18, DefectContrast = 156","\tDefectLength = 1.8, DefectWidth = 0.08, DefectContrast = 194","\tDefectLength = 1.8, DefectWidth = 0.14, DefectContrast = 213","*****Current Grade = D+, Current Surface = B*****","Defect Type Nick, Defects number = 42 on B Surface","\tDefectLength = 15.74, DefectWidth = 0.5, DefectContrast = 17","\tDefectLength = 30.32, DefectWidth = 0.54, DefectContrast = 21","\tDefectLength = 11.38, DefectWidth = 1.42, DefectContrast = 27","\tDefectLength = 14.1984, DefectWidth = 0.2592, DefectContrast = 12","\tDefectLength = 12.2016, DefectWidth = 0.1824, DefectContrast = 14","\tDefectLength = 3.8304, DefectWidth = 0.1152, DefectContrast = 7","\tDefectLength = 1.7088, DefectWidth = 1.4304, DefectContrast = 9","\tDefectLength = 0.8352, DefectWidth = 0.1344, DefectContrast = 7","\tDefectLength = 0.5184, DefectWidth = 0.3936, DefectContrast = 12","\tDefectLength = 0.3168, DefectWidth = 0.192, DefectContrast = 9","\tDefectLength = 0.624, DefectWidth = 0.1824, DefectContrast = 8","\tDefectLength = 0.672, DefectWidth = 0.3552, DefectContrast = 8","\tDefectLength = 0.4608, DefectWidth = 0.3168, DefectContrast = 10","\tDefectLength = 0.528, DefectWidth = 0.1728, DefectContrast = 8","\tDefectLength = 2.784, DefectWidth = 1.3056, DefectContrast = 7","\tDefectLength = 1.2384, DefectWidth = 0.1152, DefectContrast = 9","\tDefectLength = 11.8368, DefectWidth = 0.288, DefectContrast = 13","\tDefectLength = 0.48, DefectWidth = 0.2016, DefectContrast = 8","\tDefectLength = 1.8432, DefectWidth = 0.1344, DefectContrast = 10","\tDefectLength = 1.3152, DefectWidth = 0.2304, DefectContrast = 6","\tDefectLength = 10.1856, DefectWidth = 0.192, DefectContrast = 17","\tDefectLength = 5.3472, DefectWidth = 0.1152, DefectContrast = 8","\tDefectLength = 5.5776, DefectWidth = 0.144, DefectContrast = 8","\tDefectLength = 1.8432, DefectWidth = 0.1536, DefectContrast = 6","\tDefectLength = 0.7968, DefectWidth = 0.192, DefectContrast = 12","\tDefectLength = 3.456, DefectWidth = 0.1824, DefectContrast = 8","\tDefectLength = 1.0272, DefectWidth = 0.1152, DefectContrast = 6","\tDefectLength = 1.5456, DefectWidth = 0.1536, DefectContrast = 12","\tDefectLength = 11.8368, DefectWidth = 0.3264, DefectContrast = 11","\tDefectLength = 0.9408, DefectWidth = 0.096, DefectContrast = 7","\tDefectLength = 1.536, DefectWidth = 0.1152, DefectContrast = 7","\tDefectLength = 10.5408, DefectWidth = 0.1344, DefectContrast = 17","\tDefectLength = 2.3904, DefectWidth = 0.1248, DefectContrast = 7","\tDefectLength = 8.0352, DefectWidth = 0.2112, DefectContrast = 9","\tDefectLength = 0.5568, DefectWidth = 0.4896, DefectContrast = 6","\tDefectLength = 3.744, DefectWidth = 0.1248, DefectContrast = 7","\tDefectLength = 1.7472, DefectWidth = 0.8736, DefectContrast = 9","\tDefectLength = 0.576, DefectWidth = 0.3936, DefectContrast = 14","\tDefectLength = 11.8944, DefectWidth = 0.2496, DefectContrast = 10","\tDefectLength = 9.1776, DefectWidth = 0.1824, DefectContrast = 13","\tDefectLength = 1.9392, DefectWidth = 0.1056, DefectContrast = 5","\tDefectLength = 1.8528, DefectWidth = 0.1152, DefectContrast = 6","Defect Type Dent, Defects number = 14 on B Surface","\tDefectLength = 7.44, DefectWidth = 1.56, DefectContrast = 33","\tDefectLength = 5.26, DefectWidth = 1.24, DefectContrast = 21","\tDefectLength = 1.4304, DefectWidth = 0.1056, DefectContrast = 14","\tDefectLength = 1.104, DefectWidth = 0.1632, DefectContrast = 17","\tDefectLength = 0.2016, DefectWidth = 0.1728, DefectContrast = 21","\tDefectLength = 0.8928, DefectWidth = 0.144, DefectContrast = 27","\tDefectLength = 0.7584, DefectWidth = 0.1056, DefectContrast = 18","\tDefectLength = 0.9696, DefectWidth = 0.1056, DefectContrast = 20","\tDefectLength = 0.4224, DefectWidth = 0.096, DefectContrast = 21","\tDefectLength = 0.6336, DefectWidth = 0.0864, DefectContrast = 25","\tDefectLength = 1.6032, DefectWidth = 0.096, DefectContrast = 19","\tDefectLength = 0.2688, DefectWidth = 0.144, DefectContrast = 29","\tDefectLength = 58.6, DefectWidth = 1.48, DefectContrast = 25","\tDefectLength = 4.42, DefectWidth = 1, DefectContrast = 20"],"GradeMaxDefectTotal":[-1,194],"SurfaceItems":[{"SurfaceName":"AA","SurfaceTotalCount":[-1,0],"SurfaceGroup":{"max_defect_none":[-1,0],"max_defect_others":[0,0],"max_defect_others_Scratch":[-1,0],"max_defect_others_Nick":[-1,0],"max_defect_others_Dent":[-1,0],"max_defect_others_Crack":[0,0],"max_defect_others_Discoloration":[-1,0],"max_defect_others_GroupPindot":[-1,0],"max_defect_others_AlignmentFailed":[0,0]},"SurfaceZone":{},"DefectItems":{"LogicAnd":{"Scratch":[[-1,0]],"Nick":[[-1,0]],"Dent":[[-1,0]],"Crack":[[0,0]],"Discoloration":[[-1,0]],"DifferentScreen":[[0,0]]},"LogicOr":{"GroupPindot":[[-1,0]]}}},{"SurfaceName":"A","SurfaceTotalCount":[-1,138],"SurfaceGroup":{"max_defect_none":[-1,138],"max_defect_others":[0,0],"max_defect_others_Scratch":[-1,0],"max_defect_others_Nick":[-1,0],"max_defect_others_Dent":[-1,0],"max_defect_others_Crack":[0,0],"max_defect_others_Discoloration":[-1,0],"max_defect_others_GroupPindot":[-1,0],"max_defect_others_AlignmentFailed":[0,0]},"SurfaceZone":{},"DefectItems":{"LogicAnd":{"Scratch":[[-1,47]],"Nick":[[-1,37]],"Dent":[[-1,54]],"Crack":[[0,0]],"Discoloration":[[-1,0]]},"LogicOr":{"GroupPindot":[[-1,0]]}}},{"SurfaceName":"B","SurfaceTotalCount":[-1,56],"SurfaceGroup":{"max_defect_none":[-1,56],"max_defect_others":[0,0],"max_defect_others_Scratch":[-1,0],"max_defect_others_Nick":[-1,0],"max_defect_others_Dent":[-1,0],"max_defect_others_Crack":[0,0],"max_defect_others_Discoloration":[-1,0],"max_defect_others_GroupPindot":[-1,0],"max_defect_others_AlignmentFailed":[0,0]},"SurfaceZone":{},"DefectItems":{"LogicAnd":{"Scratch":[[-1,0]],"Nick":[[-1,42]],"Dent":[[-1,14]],"Crack":[[0,0]],"Discoloration":[[-1,0]]},"LogicOr":{"GroupPindot":[[-1,0]]}}}]}]}